<?xml version="1.0" encoding="UTF-8"?><record_update sys_domain="global" table="sys_hub_flow">
    <sys_hub_flow action="DELETE">
        <access>public</access>
        <acls/>
        <active>false</active>
        <annotation/>
        <attributes>labelCacheCleanUpExecuted=true</attributes>
        <authored_on_release_version>25000</authored_on_release_version>
        <callable_by_client_api>false</callable_by_client_api>
        <category/>
        <compiler_build/>
        <copied_from/>
        <copied_from_name/>
        <description>Steps to approve and fulfill NeedIt requests.</description>
        <flow_priority>MEDIUM</flow_priority>
        <generation_source/>
        <internal_name>needit_fulfillment</internal_name>
        <label_cache>[{"name":"Created_1.current","label":"Trigger - Record Created➛NeedIt Record","reference":"x_58872_needit_needit","reference_display":"NeedIt","type":"reference","base_type":"reference","parent_table_name":null,"column_name":null,"choices":null,"usedInstances":{"74cdd38d-6c6f-49fa-86d4-7a41eceab24a":["record"],"759a9d5a-d615-4b48-9a1e-cbc2f5c6d6c6":["record"]},"attributes":null},{"name":"Created_1.current.u_requested_for.manager","label":"Trigger - Record Created➛NeedIt Record➛Requested for➛Manager","reference":"sys_user","reference_display":"Manager","type":"reference","base_type":"reference","parent_table_name":null,"column_name":null,"choices":null,"usedInstances":{"74cdd38d-6c6f-49fa-86d4-7a41eceab24a":["approval_conditions"]},"attributes":null},{"name":"Created_1.current.u_requested_for","label":"Trigger - Record Created➛NeedIt Record➛Requested for","reference":"sys_user","reference_display":"Requested for","type":"reference","base_type":"reference","parent_table_name":null,"column_name":null,"choices":null,"usedInstances":{},"attributes":null},{"name":"74cdd38d-6c6f-49fa-86d4-7a41eceab24a.approval_state","label":"2 - Ask For Approval➛Approval State","reference":"","reference_display":"Approval State","type":"choice","base_type":"choice","parent_table_name":null,"column_name":null,"choices":null,"usedInstances":{"cdfddb15-2229-4aa3-b82e-123e9706b05a":["condition"]},"attributes":null},{"name":"759a9d5a-d615-4b48-9a1e-cbc2f5c6d6c6.record","label":"1 - Update Record➛NeedIt Record","reference":"x_58872_needit_needit","reference_display":"NeedIt","type":"reference","base_type":"reference","parent_table_name":null,"column_name":null,"choices":null,"usedInstances":{"e5375bff-84e4-4512-b72c-edb84fff1ad8":["record"],"232b8f15-7b91-4414-9cf3-db5cefa4115a":["record"]},"attributes":null}]</label_cache>
        <latest_snapshot/>
        <master_snapshot/>
        <name>NeedIt Fulfillment</name>
        <natlang/>
        <outputs/>
        <pre_compiled>false</pre_compiled>
        <remote_trigger_id/>
        <run_as>user</run_as>
        <run_with_roles/>
        <sc_callable>false</sc_callable>
        <show_draft_actions>false</show_draft_actions>
        <show_triggered_flows>false</show_triggered_flows>
        <status>draft</status>
        <sys_class_name>sys_hub_flow</sys_class_name>
        <sys_created_by>admin</sys_created_by>
        <sys_created_on>2024-04-17 09:00:43</sys_created_on>
        <sys_domain>global</sys_domain>
        <sys_domain_path>/</sys_domain_path>
        <sys_id>787a943ac325021031f0171ed4013139</sys_id>
        <sys_mod_count>32</sys_mod_count>
        <sys_name>NeedIt Fulfillment</sys_name>
        <sys_overrides/>
        <sys_package display_value="NeedIt" source="x_58872_needit">6ead8e780f603200cd674f8ce1050ed1</sys_package>
        <sys_policy/>
        <sys_scope display_value="NeedIt">6ead8e780f603200cd674f8ce1050ed1</sys_scope>
        <sys_update_name>sys_hub_flow_787a943ac325021031f0171ed4013139</sys_update_name>
        <sys_updated_by>admin</sys_updated_by>
        <sys_updated_on>2024-04-17 09:43:16</sys_updated_on>
        <type>flow</type>
    </sys_hub_flow>
    <sys_translated_text action="DELETE" query="documentkey=787a943ac325021031f0171ed4013139"/>
    <sys_variable_value action="DELETE" query="document_key=787a943ac325021031f0171ed4013139"/>
    <sys_hub_trigger_instance action="DELETE" query="flow=787a943ac325021031f0171ed4013139^sys_idNOT IN4baa503ec325021031f0171ed40131c5"/>
    <sys_hub_trigger_instance action="DELETE">
        <comment/>
        <display_text/>
        <flow display_value="NeedIt Fulfillment">787a943ac325021031f0171ed4013139</flow>
        <name>Created</name>
        <remote_sys_id/>
        <sys_created_by>admin</sys_created_by>
        <sys_created_on>2024-04-17 09:01:42</sys_created_on>
        <sys_id>4baa503ec325021031f0171ed40131c5</sys_id>
        <sys_mod_count>3</sys_mod_count>
        <sys_scope/>
        <sys_updated_by>admin</sys_updated_by>
        <sys_updated_on>2024-04-17 09:20:47</sys_updated_on>
        <trigger_definition display_value="Created">798916a0c31322002841b63b12d3ae7c</trigger_definition>
        <trigger_inputs/>
        <trigger_outputs/>
        <trigger_type>record_create</trigger_type>
    </sys_hub_trigger_instance>
    <sys_variable_value action="DELETE" query="document_key=4baa503ec325021031f0171ed40131c5"/>
    <sys_variable_value action="DELETE">
        <document>sys_hub_trigger_instance</document>
        <document_key>4baa503ec325021031f0171ed40131c5</document_key>
        <order>1</order>
        <sys_class_name>sys_variable_value</sys_class_name>
        <sys_created_by>admin</sys_created_by>
        <sys_created_on>2024-04-17 09:01:42</sys_created_on>
        <sys_id>43aa503ec325021031f0171ed40131c7</sys_id>
        <sys_mod_count>0</sys_mod_count>
        <sys_updated_by>admin</sys_updated_by>
        <sys_updated_on>2024-04-17 09:01:42</sys_updated_on>
        <value>x_58872_needit_needit</value>
        <variable display_value="Table">cfca92e0c31322002841b63b12d3ae00</variable>
    </sys_variable_value>
    <sys_variable_value action="DELETE">
        <document>sys_hub_trigger_instance</document>
        <document_key>4baa503ec325021031f0171ed40131c5</document_key>
        <order>100</order>
        <sys_class_name>sys_variable_value</sys_class_name>
        <sys_created_by>admin</sys_created_by>
        <sys_created_on>2024-04-17 09:01:42</sys_created_on>
        <sys_id>4baa503ec325021031f0171ed40131c6</sys_id>
        <sys_mod_count>0</sys_mod_count>
        <sys_updated_by>admin</sys_updated_by>
        <sys_updated_on>2024-04-17 09:01:42</sys_updated_on>
        <value>^EQ</value>
        <variable display_value="Condition">66aadea0c31322002841b63b12d3aebf</variable>
    </sys_variable_value>
    <sys_hub_flow_stage action="DELETE" query="flow=787a943ac325021031f0171ed4013139"/>
    <sys_flow_cat_variable_model action="DELETE" query="id=787a943ac325021031f0171ed4013139^sys_idNOT IN747a943ac325021031f0171ed401313a"/>
    <sys_flow_cat_variable_model action="DELETE">
        <id>787a943ac325021031f0171ed4013139</id>
        <name>NeedIt Fulfillment</name>
        <sys_created_by>admin</sys_created_by>
        <sys_created_on>2024-04-17 09:00:43</sys_created_on>
        <sys_id>747a943ac325021031f0171ed401313a</sys_id>
        <sys_mod_count>0</sys_mod_count>
        <sys_scope/>
        <sys_updated_by>admin</sys_updated_by>
        <sys_updated_on>2024-04-17 09:00:43</sys_updated_on>
    </sys_flow_cat_variable_model>
    <sys_flow_cat_variable action="DELETE" query="flow_catalog_model=747a943ac325021031f0171ed401313a"/>
    <sys_hub_flow_input action="DELETE" query="model=787a943ac325021031f0171ed4013139^sys_idNOT IN15ecd4fec325021031f0171ed4013189,a1ecd4fec325021031f0171ed4013194"/>
    <sys_hub_flow_input action="DELETE">
        <active>true</active>
        <array>false</array>
        <array_denormalized>false</array_denormalized>
        <attributes>element_mapping_provider=com.glide.flow_design.action.data.FlowDesignVariableMapper,uiType=document_id</attributes>
        <audit>false</audit>
        <calculation><![CDATA[(function calculatedFieldValue(current) {

	// Add your code here
	return '';  // return the calculated value

})(current);]]></calculation>
        <choice/>
        <choice_field/>
        <choice_table/>
        <column_label/>
        <comments/>
        <create_roles/>
        <default_value/>
        <defaultsort/>
        <delete_roles/>
        <dependent>table_name</dependent>
        <dependent_on_field>table_name</dependent_on_field>
        <display>false</display>
        <dynamic_creation>false</dynamic_creation>
        <dynamic_creation_script/>
        <dynamic_default_value/>
        <dynamic_ref_qual/>
        <element>current</element>
        <element_reference>false</element_reference>
        <foreign_database/>
        <formula/>
        <function_definition/>
        <function_field>false</function_field>
        <help/>
        <hint/>
        <internal_type display_value="">document_id</internal_type>
        <label>Record</label>
        <mandatory>true</mandatory>
        <max_length>200</max_length>
        <model display_value="NeedIt Fulfillment">787a943ac325021031f0171ed4013139</model>
        <model_id>787a943ac325021031f0171ed4013139</model_id>
        <model_table>sys_hub_flow</model_table>
        <name>var__m_sys_hub_flow_input_787a943ac325021031f0171ed4013139</name>
        <next_element/>
        <order>100</order>
        <primary>false</primary>
        <read_only>false</read_only>
        <read_roles/>
        <reference/>
        <reference_cascade_rule/>
        <reference_floats>false</reference_floats>
        <reference_key/>
        <reference_qual/>
        <reference_qual_condition/>
        <reference_type/>
        <sizeclass/>
        <spell_check>false</spell_check>
        <staged>false</staged>
        <sys_class_name>sys_hub_flow_input</sys_class_name>
        <sys_created_by>admin</sys_created_by>
        <sys_created_on>2024-04-17 09:11:25</sys_created_on>
        <sys_id>15ecd4fec325021031f0171ed4013189</sys_id>
        <sys_mod_count>0</sys_mod_count>
        <sys_name/>
        <sys_package/>
        <sys_policy/>
        <sys_scope display_value="NeedIt">6ead8e780f603200cd674f8ce1050ed1</sys_scope>
        <sys_update_name/>
        <sys_updated_by>admin</sys_updated_by>
        <sys_updated_on>2024-04-17 09:11:25</sys_updated_on>
        <table_reference>false</table_reference>
        <text_index>false</text_index>
        <unique>false</unique>
        <use_dependent_field>true</use_dependent_field>
        <use_dynamic_default>false</use_dynamic_default>
        <use_reference_qualifier>simple</use_reference_qualifier>
        <virtual>false</virtual>
        <virtual_type>script</virtual_type>
        <widget/>
        <write_roles/>
        <xml_view>false</xml_view>
    </sys_hub_flow_input>
    <sys_hub_action_input_action_instance action="DELETE" query="action_input=15ecd4fec325021031f0171ed4013189"/>
    <sys_hub_flow_input action="DELETE">
        <active>true</active>
        <array>false</array>
        <array_denormalized>false</array_denormalized>
        <attributes>element_mapping_provider=com.glide.flow_design.action.data.FlowDesignVariableMapper,test_input_hidden=true,uiType=table_name</attributes>
        <audit>false</audit>
        <calculation><![CDATA[(function calculatedFieldValue(current) {

	// Add your code here
	return '';  // return the calculated value

})(current);]]></calculation>
        <choice/>
        <choice_field/>
        <choice_table/>
        <column_label/>
        <comments/>
        <create_roles/>
        <default_value/>
        <defaultsort/>
        <delete_roles/>
        <dependent/>
        <dependent_on_field/>
        <display>false</display>
        <dynamic_creation>false</dynamic_creation>
        <dynamic_creation_script/>
        <dynamic_default_value/>
        <dynamic_ref_qual/>
        <element>table_name</element>
        <element_reference>false</element_reference>
        <foreign_database/>
        <formula/>
        <function_definition/>
        <function_field>false</function_field>
        <help/>
        <hint/>
        <internal_type display_value="">table_name</internal_type>
        <label>Table Name</label>
        <mandatory>false</mandatory>
        <max_length>200</max_length>
        <model display_value="NeedIt Fulfillment">787a943ac325021031f0171ed4013139</model>
        <model_id>787a943ac325021031f0171ed4013139</model_id>
        <model_table>sys_hub_flow</model_table>
        <name>var__m_sys_hub_flow_input_787a943ac325021031f0171ed4013139</name>
        <next_element/>
        <order>101</order>
        <primary>false</primary>
        <read_only>false</read_only>
        <read_roles/>
        <reference/>
        <reference_cascade_rule/>
        <reference_floats>false</reference_floats>
        <reference_key/>
        <reference_qual/>
        <reference_qual_condition/>
        <reference_type/>
        <sizeclass/>
        <spell_check>false</spell_check>
        <staged>false</staged>
        <sys_class_name>sys_hub_flow_input</sys_class_name>
        <sys_created_by>admin</sys_created_by>
        <sys_created_on>2024-04-17 09:11:25</sys_created_on>
        <sys_id>a1ecd4fec325021031f0171ed4013194</sys_id>
        <sys_mod_count>0</sys_mod_count>
        <sys_name/>
        <sys_package/>
        <sys_policy/>
        <sys_scope display_value="NeedIt">6ead8e780f603200cd674f8ce1050ed1</sys_scope>
        <sys_update_name/>
        <sys_updated_by>admin</sys_updated_by>
        <sys_updated_on>2024-04-17 09:11:25</sys_updated_on>
        <table_reference>false</table_reference>
        <text_index>false</text_index>
        <unique>false</unique>
        <use_dependent_field>false</use_dependent_field>
        <use_dynamic_default>false</use_dynamic_default>
        <use_reference_qualifier>simple</use_reference_qualifier>
        <virtual>false</virtual>
        <virtual_type>script</virtual_type>
        <widget/>
        <write_roles/>
        <xml_view>false</xml_view>
    </sys_hub_flow_input>
    <sys_hub_action_input_action_instance action="DELETE" query="action_input=a1ecd4fec325021031f0171ed4013194"/>
    <sys_hub_flow_output action="DELETE" query="model=787a943ac325021031f0171ed4013139"/>
    <sys_hub_alias_mapping action="DELETE" query="source_id=787a943ac325021031f0171ed4013139"/>
    <sys_hub_action_instance action="DELETE" query="flow=787a943ac325021031f0171ed4013139^sys_idNOT IN551c18fac325021031f0171ed40131c1,5c3bd0bac325021031f0171ed40131de,8a8c507ec325021031f0171ed4013165,a9bad43ec325021031f0171ed40131fc"/>
    <sys_hub_action_instance action="DELETE">
        <action_inputs/>
        <action_inputs/>
        <action_type display_value="Update Record">f9d01dd2c31332002841b63b12d3aea1</action_type>
        <action_type_parent/>
        <attributes/>
        <comment>Update NeedIt State to Approved</comment>
        <compiled_snapshot/>
        <display_text/>
        <flow display_value="NeedIt Fulfillment">787a943ac325021031f0171ed4013139</flow>
        <generation_source/>
        <order>4</order>
        <parent_ui_id>cdfddb15-2229-4aa3-b82e-123e9706b05a</parent_ui_id>
        <sys_class_name>sys_hub_action_instance</sys_class_name>
        <sys_created_by>admin</sys_created_by>
        <sys_created_on>2024-04-17 09:07:51</sys_created_on>
        <sys_id>551c18fac325021031f0171ed40131c1</sys_id>
        <sys_mod_count>6</sys_mod_count>
        <sys_scope display_value="NeedIt">6ead8e780f603200cd674f8ce1050ed1</sys_scope>
        <sys_updated_by>admin</sys_updated_by>
        <sys_updated_on>2024-04-17 09:09:00</sys_updated_on>
        <ui_id>232b8f15-7b91-4414-9cf3-db5cefa4115a</ui_id>
    </sys_hub_action_instance>
    <sys_variable_value action="DELETE" query="document_key=551c18fac325021031f0171ed40131c1"/>
    <sys_variable_value action="DELETE">
        <document>sys_hub_action_instance</document>
        <document_key>551c18fac325021031f0171ed40131c1</document_key>
        <order>50</order>
        <sys_class_name>sys_variable_value</sys_class_name>
        <sys_created_by>admin</sys_created_by>
        <sys_created_on>2024-04-17 09:09:00</sys_created_on>
        <sys_id>8a5c54bec325021031f0171ed401310d</sys_id>
        <sys_mod_count>0</sys_mod_count>
        <sys_updated_by>admin</sys_updated_by>
        <sys_updated_on>2024-04-17 09:09:00</sys_updated_on>
        <value>x_58872_needit_needit</value>
        <variable display_value="Table">b5d01916c31332002841b63b12d3aec9</variable>
    </sys_variable_value>
    <sys_variable_value action="DELETE">
        <document>sys_hub_action_instance</document>
        <document_key>551c18fac325021031f0171ed40131c1</document_key>
        <order>100</order>
        <sys_class_name>sys_variable_value</sys_class_name>
        <sys_created_by>admin</sys_created_by>
        <sys_created_on>2024-04-17 09:09:00</sys_created_on>
        <sys_id>c65c54bec325021031f0171ed401310d</sys_id>
        <sys_mod_count>0</sys_mod_count>
        <sys_updated_by>admin</sys_updated_by>
        <sys_updated_on>2024-04-17 09:09:00</sys_updated_on>
        <value>state=15</value>
        <variable display_value="Fields">02d01916c31332002841b63b12d3aeee</variable>
    </sys_variable_value>
    <sys_element_mapping action="DELETE" query="id=551c18fac325021031f0171ed40131c1"/>
    <sys_element_mapping action="DELETE">
        <field>record</field>
        <id>551c18fac325021031f0171ed40131c1</id>
        <sys_created_by>admin</sys_created_by>
        <sys_created_on>2024-04-17 09:09:00</sys_created_on>
        <sys_id>465c54bec325021031f0171ed401310d</sys_id>
        <sys_mod_count>0</sys_mod_count>
        <sys_updated_by>admin</sys_updated_by>
        <sys_updated_on>2024-04-17 09:09:00</sys_updated_on>
        <table>var__m_sys_hub_action_input_f9d01dd2c31332002841b63b12d3aea1</table>
        <value>{{759a9d5a-d615-4b48-9a1e-cbc2f5c6d6c6.record}}</value>
    </sys_element_mapping>
    <sys_element_mapping action="DELETE">
        <field>table_name</field>
        <id>551c18fac325021031f0171ed40131c1</id>
        <sys_created_by>admin</sys_created_by>
        <sys_created_on>2024-04-17 09:09:00</sys_created_on>
        <sys_id>ce5c54bec325021031f0171ed401310c</sys_id>
        <sys_mod_count>0</sys_mod_count>
        <sys_updated_by>admin</sys_updated_by>
        <sys_updated_on>2024-04-17 09:09:00</sys_updated_on>
        <table>var__m_sys_hub_action_input_f9d01dd2c31332002841b63b12d3aea1</table>
        <value/>
    </sys_element_mapping>
    <sys_element_mapping action="DELETE">
        <field>values</field>
        <id>551c18fac325021031f0171ed40131c1</id>
        <sys_created_by>admin</sys_created_by>
        <sys_created_on>2024-04-17 09:09:00</sys_created_on>
        <sys_id>825c54bec325021031f0171ed401310d</sys_id>
        <sys_mod_count>0</sys_mod_count>
        <sys_updated_by>admin</sys_updated_by>
        <sys_updated_on>2024-04-17 09:09:00</sys_updated_on>
        <table>var__m_sys_hub_action_input_f9d01dd2c31332002841b63b12d3aea1</table>
        <value/>
    </sys_element_mapping>
    <sys_hub_input_scripts action="DELETE" query="instance=551c18fac325021031f0171ed40131c1"/>
    <sys_hub_alias_mapping action="DELETE" query="source_id=551c18fac325021031f0171ed40131c1"/>
    <sys_hub_action_instance action="DELETE">
        <action_inputs/>
        <action_inputs/>
        <action_type display_value="Ask For Approval">f8f2e9920b10030085c083eb37673abd</action_type>
        <action_type_parent/>
        <attributes/>
        <comment>Get approval from Requested for's Manager</comment>
        <compiled_snapshot/>
        <display_text/>
        <flow display_value="NeedIt Fulfillment">787a943ac325021031f0171ed4013139</flow>
        <generation_source/>
        <order>2</order>
        <parent_ui_id/>
        <sys_class_name>sys_hub_action_instance</sys_class_name>
        <sys_created_by>admin</sys_created_by>
        <sys_created_on>2024-04-17 09:03:57</sys_created_on>
        <sys_id>5c3bd0bac325021031f0171ed40131de</sys_id>
        <sys_mod_count>4</sys_mod_count>
        <sys_scope display_value="NeedIt">6ead8e780f603200cd674f8ce1050ed1</sys_scope>
        <sys_updated_by>admin</sys_updated_by>
        <sys_updated_on>2024-04-17 09:06:07</sys_updated_on>
        <ui_id>74cdd38d-6c6f-49fa-86d4-7a41eceab24a</ui_id>
    </sys_hub_action_instance>
    <sys_variable_value action="DELETE" query="document_key=5c3bd0bac325021031f0171ed40131de"/>
    <sys_variable_value action="DELETE">
        <document>sys_hub_action_instance</document>
        <document_key>5c3bd0bac325021031f0171ed40131de</document_key>
        <order>5</order>
        <sys_class_name>sys_variable_value</sys_class_name>
        <sys_created_by>admin</sys_created_by>
        <sys_created_on>2024-04-17 09:06:07</sys_created_on>
        <sys_id>37ab1c7ec325021031f0171ed401317b</sys_id>
        <sys_mod_count>0</sys_mod_count>
        <sys_updated_by>admin</sys_updated_by>
        <sys_updated_on>2024-04-17 09:06:07</sys_updated_on>
        <value/>
        <variable display_value="Due Date">c5f2e9920b10030085c083eb37673af9</variable>
    </sys_variable_value>
    <sys_variable_value action="DELETE">
        <document>sys_hub_action_instance</document>
        <document_key>5c3bd0bac325021031f0171ed40131de</document_key>
        <order>3</order>
        <sys_class_name>sys_variable_value</sys_class_name>
        <sys_created_by>admin</sys_created_by>
        <sys_created_on>2024-04-17 09:06:07</sys_created_on>
        <sys_id>73ab1c7ec325021031f0171ed401317b</sys_id>
        <sys_mod_count>0</sys_mod_count>
        <sys_updated_by>admin</sys_updated_by>
        <sys_updated_on>2024-04-17 09:06:07</sys_updated_on>
        <value>approval_history</value>
        <variable display_value="Journal Field">c1f2e9920b10030085c083eb37673ae3</variable>
    </sys_variable_value>
    <sys_variable_value action="DELETE">
        <document>sys_hub_action_instance</document>
        <document_key>5c3bd0bac325021031f0171ed40131de</document_key>
        <order>2</order>
        <sys_class_name>sys_variable_value</sys_class_name>
        <sys_created_by>admin</sys_created_by>
        <sys_created_on>2024-04-17 09:06:07</sys_created_on>
        <sys_id>bfab1c7ec325021031f0171ed401317a</sys_id>
        <sys_mod_count>0</sys_mod_count>
        <sys_updated_by>admin</sys_updated_by>
        <sys_updated_on>2024-04-17 09:06:07</sys_updated_on>
        <value>approval</value>
        <variable display_value="Approval Field">01f2e9920b10030085c083eb37673ad8</variable>
    </sys_variable_value>
    <sys_variable_value action="DELETE">
        <document>sys_hub_action_instance</document>
        <document_key>5c3bd0bac325021031f0171ed40131de</document_key>
        <order>1</order>
        <sys_class_name>sys_variable_value</sys_class_name>
        <sys_created_by>admin</sys_created_by>
        <sys_created_on>2024-04-17 09:06:07</sys_created_on>
        <sys_id>f7ab1c7ec325021031f0171ed401317b</sys_id>
        <sys_mod_count>0</sys_mod_count>
        <sys_updated_by>admin</sys_updated_by>
        <sys_updated_on>2024-04-17 09:06:07</sys_updated_on>
        <value>x_58872_needit_needit</value>
        <variable display_value="Table">bcf2e9920b10030085c083eb37673acc</variable>
    </sys_variable_value>
    <sys_element_mapping action="DELETE" query="id=5c3bd0bac325021031f0171ed40131de"/>
    <sys_element_mapping action="DELETE">
        <field>approval_conditions</field>
        <id>5c3bd0bac325021031f0171ed40131de</id>
        <sys_created_by>admin</sys_created_by>
        <sys_created_on>2024-04-17 09:06:07</sys_created_on>
        <sys_id>7bab1c7ec325021031f0171ed401317a</sys_id>
        <sys_mod_count>0</sys_mod_count>
        <sys_updated_by>admin</sys_updated_by>
        <sys_updated_on>2024-04-17 09:06:07</sys_updated_on>
        <table>var__m_sys_hub_action_input_f8f2e9920b10030085c083eb37673abd</table>
        <value>ApprovesRejectsAnyU[{{Created_1.current.u_requested_for.manager}}]</value>
    </sys_element_mapping>
    <sys_element_mapping action="DELETE">
        <field>approval_field</field>
        <id>5c3bd0bac325021031f0171ed40131de</id>
        <sys_created_by>admin</sys_created_by>
        <sys_created_on>2024-04-17 09:06:07</sys_created_on>
        <sys_id>bbab503ec325021031f0171ed40131cd</sys_id>
        <sys_mod_count>0</sys_mod_count>
        <sys_updated_by>admin</sys_updated_by>
        <sys_updated_on>2024-04-17 09:06:07</sys_updated_on>
        <table>var__m_sys_hub_action_input_f8f2e9920b10030085c083eb37673abd</table>
        <value/>
    </sys_element_mapping>
    <sys_element_mapping action="DELETE">
        <field>due_date</field>
        <id>5c3bd0bac325021031f0171ed40131de</id>
        <sys_created_by>admin</sys_created_by>
        <sys_created_on>2024-04-17 09:06:07</sys_created_on>
        <sys_id>f3ab503ec325021031f0171ed40131ce</sys_id>
        <sys_mod_count>0</sys_mod_count>
        <sys_updated_by>admin</sys_updated_by>
        <sys_updated_on>2024-04-17 09:06:07</sys_updated_on>
        <table>var__m_sys_hub_action_input_f8f2e9920b10030085c083eb37673abd</table>
        <value>{"action":"none","date_type":"actual","date":"{{}}","duration":1,"duration_type":"days","schedule":"","schedule_label":""}</value>
    </sys_element_mapping>
    <sys_element_mapping action="DELETE">
        <field>journal_field</field>
        <id>5c3bd0bac325021031f0171ed40131de</id>
        <sys_created_by>admin</sys_created_by>
        <sys_created_on>2024-04-17 09:06:07</sys_created_on>
        <sys_id>7fab503ec325021031f0171ed40131cd</sys_id>
        <sys_mod_count>0</sys_mod_count>
        <sys_updated_by>admin</sys_updated_by>
        <sys_updated_on>2024-04-17 09:06:07</sys_updated_on>
        <table>var__m_sys_hub_action_input_f8f2e9920b10030085c083eb37673abd</table>
        <value/>
    </sys_element_mapping>
    <sys_element_mapping action="DELETE">
        <field>record</field>
        <id>5c3bd0bac325021031f0171ed40131de</id>
        <sys_created_by>admin</sys_created_by>
        <sys_created_on>2024-04-17 09:06:07</sys_created_on>
        <sys_id>33ab503ec325021031f0171ed40131ce</sys_id>
        <sys_mod_count>0</sys_mod_count>
        <sys_updated_by>admin</sys_updated_by>
        <sys_updated_on>2024-04-17 09:06:07</sys_updated_on>
        <table>var__m_sys_hub_action_input_f8f2e9920b10030085c083eb37673abd</table>
        <value>{{Created_1.current}}</value>
    </sys_element_mapping>
    <sys_element_mapping action="DELETE">
        <field>table</field>
        <id>5c3bd0bac325021031f0171ed40131de</id>
        <sys_created_by>admin</sys_created_by>
        <sys_created_on>2024-04-17 09:06:07</sys_created_on>
        <sys_id>3fab1c7ec325021031f0171ed401317a</sys_id>
        <sys_mod_count>0</sys_mod_count>
        <sys_updated_by>admin</sys_updated_by>
        <sys_updated_on>2024-04-17 09:06:07</sys_updated_on>
        <table>var__m_sys_hub_action_input_f8f2e9920b10030085c083eb37673abd</table>
        <value/>
    </sys_element_mapping>
    <sys_hub_input_scripts action="DELETE" query="instance=5c3bd0bac325021031f0171ed40131de"/>
    <sys_hub_alias_mapping action="DELETE" query="source_id=5c3bd0bac325021031f0171ed40131de"/>
    <sys_hub_action_instance action="DELETE">
        <action_inputs/>
        <action_inputs/>
        <action_type display_value="Update Record">f9d01dd2c31332002841b63b12d3aea1</action_type>
        <action_type_parent/>
        <attributes/>
        <comment>Update NeedIt State to Closed Complete</comment>
        <compiled_snapshot/>
        <display_text/>
        <flow display_value="NeedIt Fulfillment">787a943ac325021031f0171ed4013139</flow>
        <generation_source/>
        <order>6</order>
        <parent_ui_id>b4a2010b-b985-4530-a999-29fa931b3ad2</parent_ui_id>
        <sys_class_name>sys_hub_action_instance</sys_class_name>
        <sys_created_by>admin</sys_created_by>
        <sys_created_on>2024-04-17 09:09:49</sys_created_on>
        <sys_id>8a8c507ec325021031f0171ed4013165</sys_id>
        <sys_mod_count>6</sys_mod_count>
        <sys_scope display_value="NeedIt">6ead8e780f603200cd674f8ce1050ed1</sys_scope>
        <sys_updated_by>admin</sys_updated_by>
        <sys_updated_on>2024-04-17 09:10:14</sys_updated_on>
        <ui_id>e5375bff-84e4-4512-b72c-edb84fff1ad8</ui_id>
    </sys_hub_action_instance>
    <sys_variable_value action="DELETE" query="document_key=8a8c507ec325021031f0171ed4013165"/>
    <sys_variable_value action="DELETE">
        <document>sys_hub_action_instance</document>
        <document_key>8a8c507ec325021031f0171ed4013165</document_key>
        <order>100</order>
        <sys_class_name>sys_variable_value</sys_class_name>
        <sys_created_by>admin</sys_created_by>
        <sys_created_on>2024-04-17 09:10:12</sys_created_on>
        <sys_id>3b9cd0bec325021031f0171ed40131b5</sys_id>
        <sys_mod_count>0</sys_mod_count>
        <sys_updated_by>admin</sys_updated_by>
        <sys_updated_on>2024-04-17 09:10:12</sys_updated_on>
        <value>state=3</value>
        <variable display_value="Fields">02d01916c31332002841b63b12d3aeee</variable>
    </sys_variable_value>
    <sys_variable_value action="DELETE">
        <document>sys_hub_action_instance</document>
        <document_key>8a8c507ec325021031f0171ed4013165</document_key>
        <order>50</order>
        <sys_class_name>sys_variable_value</sys_class_name>
        <sys_created_by>admin</sys_created_by>
        <sys_created_on>2024-04-17 09:10:13</sys_created_on>
        <sys_id>fb9cd0bec325021031f0171ed40131b5</sys_id>
        <sys_mod_count>0</sys_mod_count>
        <sys_updated_by>admin</sys_updated_by>
        <sys_updated_on>2024-04-17 09:10:13</sys_updated_on>
        <value>x_58872_needit_needit</value>
        <variable display_value="Table">b5d01916c31332002841b63b12d3aec9</variable>
    </sys_variable_value>
    <sys_element_mapping action="DELETE" query="id=8a8c507ec325021031f0171ed4013165"/>
    <sys_element_mapping action="DELETE">
        <field>record</field>
        <id>8a8c507ec325021031f0171ed4013165</id>
        <sys_created_by>admin</sys_created_by>
        <sys_created_on>2024-04-17 09:10:12</sys_created_on>
        <sys_id>b79cd0bec325021031f0171ed40131b5</sys_id>
        <sys_mod_count>0</sys_mod_count>
        <sys_updated_by>admin</sys_updated_by>
        <sys_updated_on>2024-04-17 09:10:12</sys_updated_on>
        <table>var__m_sys_hub_action_input_f9d01dd2c31332002841b63b12d3aea1</table>
        <value>{{759a9d5a-d615-4b48-9a1e-cbc2f5c6d6c6.record}}</value>
    </sys_element_mapping>
    <sys_element_mapping action="DELETE">
        <field>table_name</field>
        <id>8a8c507ec325021031f0171ed4013165</id>
        <sys_created_by>admin</sys_created_by>
        <sys_created_on>2024-04-17 09:10:12</sys_created_on>
        <sys_id>339cd0bec325021031f0171ed40131b5</sys_id>
        <sys_mod_count>0</sys_mod_count>
        <sys_updated_by>admin</sys_updated_by>
        <sys_updated_on>2024-04-17 09:10:12</sys_updated_on>
        <table>var__m_sys_hub_action_input_f9d01dd2c31332002841b63b12d3aea1</table>
        <value/>
    </sys_element_mapping>
    <sys_element_mapping action="DELETE">
        <field>values</field>
        <id>8a8c507ec325021031f0171ed4013165</id>
        <sys_created_by>admin</sys_created_by>
        <sys_created_on>2024-04-17 09:10:12</sys_created_on>
        <sys_id>f39cd0bec325021031f0171ed40131b5</sys_id>
        <sys_mod_count>0</sys_mod_count>
        <sys_updated_by>admin</sys_updated_by>
        <sys_updated_on>2024-04-17 09:10:12</sys_updated_on>
        <table>var__m_sys_hub_action_input_f9d01dd2c31332002841b63b12d3aea1</table>
        <value/>
    </sys_element_mapping>
    <sys_hub_input_scripts action="DELETE" query="instance=8a8c507ec325021031f0171ed4013165"/>
    <sys_hub_alias_mapping action="DELETE" query="source_id=8a8c507ec325021031f0171ed4013165"/>
    <sys_hub_action_instance action="DELETE">
        <action_inputs/>
        <action_inputs/>
        <action_type display_value="Update Record">f9d01dd2c31332002841b63b12d3aea1</action_type>
        <action_type_parent/>
        <attributes/>
        <comment>Set State to Awaiting Approval</comment>
        <compiled_snapshot/>
        <display_text/>
        <flow display_value="NeedIt Fulfillment">787a943ac325021031f0171ed4013139</flow>
        <generation_source/>
        <order>1</order>
        <parent_ui_id/>
        <sys_class_name>sys_hub_action_instance</sys_class_name>
        <sys_created_by>admin</sys_created_by>
        <sys_created_on>2024-04-17 09:01:51</sys_created_on>
        <sys_id>a9bad43ec325021031f0171ed40131fc</sys_id>
        <sys_mod_count>18</sys_mod_count>
        <sys_scope display_value="NeedIt">6ead8e780f603200cd674f8ce1050ed1</sys_scope>
        <sys_updated_by>admin</sys_updated_by>
        <sys_updated_on>2024-04-17 09:43:06</sys_updated_on>
        <ui_id>759a9d5a-d615-4b48-9a1e-cbc2f5c6d6c6</ui_id>
    </sys_hub_action_instance>
    <sys_variable_value action="DELETE" query="document_key=a9bad43ec325021031f0171ed40131fc"/>
    <sys_variable_value action="DELETE">
        <document>sys_hub_action_instance</document>
        <document_key>a9bad43ec325021031f0171ed40131fc</document_key>
        <order>50</order>
        <sys_class_name>sys_variable_value</sys_class_name>
        <sys_created_by>admin</sys_created_by>
        <sys_created_on>2024-04-17 09:02:13</sys_created_on>
        <sys_id>b6ca583ec325021031f0171ed40131fa</sys_id>
        <sys_mod_count>0</sys_mod_count>
        <sys_updated_by>admin</sys_updated_by>
        <sys_updated_on>2024-04-17 09:02:13</sys_updated_on>
        <value>x_58872_needit_needit</value>
        <variable display_value="Table">b5d01916c31332002841b63b12d3aec9</variable>
    </sys_variable_value>
    <sys_variable_value action="DELETE">
        <document>sys_hub_action_instance</document>
        <document_key>a9bad43ec325021031f0171ed40131fc</document_key>
        <order>100</order>
        <sys_class_name>sys_variable_value</sys_class_name>
        <sys_created_by>admin</sys_created_by>
        <sys_created_on>2024-04-17 09:02:13</sys_created_on>
        <sys_id>f2ca583ec325021031f0171ed40131fa</sys_id>
        <sys_mod_count>4</sys_mod_count>
        <sys_updated_by>admin</sys_updated_by>
        <sys_updated_on>2024-04-17 09:43:06</sys_updated_on>
        <value>state=14^assigned_to={"display":"Fred Luddy","value":"5137153cc611227c000bbd1bd8cd2005","table":"sys_user","sys_id":"5137153cc611227c000bbd1bd8cd2005"}</value>
        <variable display_value="Fields">02d01916c31332002841b63b12d3aeee</variable>
    </sys_variable_value>
    <sys_element_mapping action="DELETE" query="id=a9bad43ec325021031f0171ed40131fc"/>
    <sys_element_mapping action="DELETE">
        <field>record</field>
        <id>a9bad43ec325021031f0171ed40131fc</id>
        <sys_created_by>admin</sys_created_by>
        <sys_created_on>2024-04-17 09:02:13</sys_created_on>
        <sys_id>72ca583ec325021031f0171ed40131fa</sys_id>
        <sys_mod_count>0</sys_mod_count>
        <sys_updated_by>admin</sys_updated_by>
        <sys_updated_on>2024-04-17 09:02:13</sys_updated_on>
        <table>var__m_sys_hub_action_input_f9d01dd2c31332002841b63b12d3aea1</table>
        <value>{{Created_1.current}}</value>
    </sys_element_mapping>
    <sys_element_mapping action="DELETE">
        <field>table_name</field>
        <id>a9bad43ec325021031f0171ed40131fc</id>
        <sys_created_by>admin</sys_created_by>
        <sys_created_on>2024-04-17 09:02:13</sys_created_on>
        <sys_id>f6ca583ec325021031f0171ed40131f9</sys_id>
        <sys_mod_count>0</sys_mod_count>
        <sys_updated_by>admin</sys_updated_by>
        <sys_updated_on>2024-04-17 09:02:13</sys_updated_on>
        <table>var__m_sys_hub_action_input_f9d01dd2c31332002841b63b12d3aea1</table>
        <value/>
    </sys_element_mapping>
    <sys_element_mapping action="DELETE">
        <field>values</field>
        <id>a9bad43ec325021031f0171ed40131fc</id>
        <sys_created_by>admin</sys_created_by>
        <sys_created_on>2024-04-17 09:02:13</sys_created_on>
        <sys_id>beca583ec325021031f0171ed40131f9</sys_id>
        <sys_mod_count>0</sys_mod_count>
        <sys_updated_by>admin</sys_updated_by>
        <sys_updated_on>2024-04-17 09:02:13</sys_updated_on>
        <table>var__m_sys_hub_action_input_f9d01dd2c31332002841b63b12d3aea1</table>
        <value/>
    </sys_element_mapping>
    <sys_hub_input_scripts action="DELETE" query="instance=a9bad43ec325021031f0171ed40131fc"/>
    <sys_hub_alias_mapping action="DELETE" query="source_id=a9bad43ec325021031f0171ed40131fc"/>
    <sys_hub_sub_flow_instance action="DELETE" query="flow=787a943ac325021031f0171ed4013139"/>
    <sys_hub_flow_logic action="DELETE" query="flow=787a943ac325021031f0171ed4013139^sys_idNOT INd46cd0bec325021031f0171ed40131b0,e6bb987ec325021031f0171ed4013195"/>
    <sys_hub_flow_logic action="DELETE">
        <attributes/>
        <block display_value="">c28c9cbec325021031f0171ed40131b4</block>
        <comment/>
        <connected_to>cdfddb15-2229-4aa3-b82e-123e9706b05a</connected_to>
        <decision_table/>
        <decision_table_inputs/>
        <display_text/>
        <extended_inputs/>
        <flow display_value="NeedIt Fulfillment">787a943ac325021031f0171ed4013139</flow>
        <flow_variable/>
        <flow_variables_assigned/>
        <generation_source/>
        <inputs/>
        <logic_definition display_value="Else">1f781bf3c32232002841b63b12d3aee6</logic_definition>
        <order>5</order>
        <outputs_assigned/>
        <outputs_to_assign/>
        <parent_ui_id/>
        <sys_class_name>sys_hub_flow_logic</sys_class_name>
        <sys_created_by>admin</sys_created_by>
        <sys_created_on>2024-04-17 09:09:09</sys_created_on>
        <sys_id>d46cd0bec325021031f0171ed40131b0</sys_id>
        <sys_mod_count>3</sys_mod_count>
        <sys_scope display_value="NeedIt">6ead8e780f603200cd674f8ce1050ed1</sys_scope>
        <sys_updated_by>admin</sys_updated_by>
        <sys_updated_on>2024-04-17 09:09:49</sys_updated_on>
        <ui_id>b4a2010b-b985-4530-a999-29fa931b3ad2</ui_id>
        <workflow_inputs/>
        <workflow_reference/>
    </sys_hub_flow_logic>
    <sys_variable_value action="DELETE" query="document_key=d46cd0bec325021031f0171ed40131b0"/>
    <sys_hub_flow_logic_ext_input action="DELETE" query="model=d46cd0bec325021031f0171ed40131b0"/>
    <sys_hub_input_scripts action="DELETE" query="instance=d46cd0bec325021031f0171ed40131b0"/>
    <sys_hub_flow_logic action="DELETE">
        <attributes/>
        <block display_value="">5d1c18fac325021031f0171ed40131c4</block>
        <comment/>
        <connected_to/>
        <decision_table/>
        <decision_table_inputs/>
        <display_text/>
        <extended_inputs/>
        <flow display_value="NeedIt Fulfillment">787a943ac325021031f0171ed4013139</flow>
        <flow_variable/>
        <flow_variables_assigned/>
        <generation_source/>
        <inputs/>
        <inputs/>
        <logic_definition display_value="If">af4e1945c3e232002841b63b12d3ae3e</logic_definition>
        <order>3</order>
        <outputs_assigned/>
        <outputs_to_assign/>
        <parent_ui_id/>
        <sys_class_name>sys_hub_flow_logic</sys_class_name>
        <sys_created_by>admin</sys_created_by>
        <sys_created_on>2024-04-17 09:06:18</sys_created_on>
        <sys_id>e6bb987ec325021031f0171ed4013195</sys_id>
        <sys_mod_count>5</sys_mod_count>
        <sys_scope display_value="NeedIt">6ead8e780f603200cd674f8ce1050ed1</sys_scope>
        <sys_updated_by>admin</sys_updated_by>
        <sys_updated_on>2024-04-17 09:07:51</sys_updated_on>
        <ui_id>cdfddb15-2229-4aa3-b82e-123e9706b05a</ui_id>
        <workflow_inputs/>
        <workflow_reference/>
    </sys_hub_flow_logic>
    <sys_variable_value action="DELETE" query="document_key=e6bb987ec325021031f0171ed4013195"/>
    <sys_variable_value action="DELETE">
        <document>sys_hub_flow_logic</document>
        <document_key>e6bb987ec325021031f0171ed4013195</document_key>
        <order>10</order>
        <sys_class_name>sys_variable_value</sys_class_name>
        <sys_created_by>admin</sys_created_by>
        <sys_created_on>2024-04-17 09:07:30</sys_created_on>
        <sys_id>040cd0bec325021031f0171ed401317f</sys_id>
        <sys_mod_count>0</sys_mod_count>
        <sys_updated_by>admin</sys_updated_by>
        <sys_updated_on>2024-04-17 09:07:30</sys_updated_on>
        <value>Request Approved</value>
        <variable display_value="Condition Label">f0af19c1c32632002841b63b12d3aea3</variable>
    </sys_variable_value>
    <sys_element_mapping action="DELETE" query="id=e6bb987ec325021031f0171ed4013195"/>
    <sys_element_mapping action="DELETE">
        <field>condition</field>
        <id>e6bb987ec325021031f0171ed4013195</id>
        <sys_created_by>admin</sys_created_by>
        <sys_created_on>2024-04-17 09:07:30</sys_created_on>
        <sys_id>800cd0bec325021031f0171ed401317f</sys_id>
        <sys_mod_count>0</sys_mod_count>
        <sys_updated_by>admin</sys_updated_by>
        <sys_updated_on>2024-04-17 09:07:30</sys_updated_on>
        <table>var__m_sys_hub_flow_logic_input_af4e1945c3e232002841b63b12d3ae3e</table>
        <value>{{74cdd38d-6c6f-49fa-86d4-7a41eceab24a.approval_state}}=approved</value>
    </sys_element_mapping>
    <sys_element_mapping action="DELETE">
        <field>condition_name</field>
        <id>e6bb987ec325021031f0171ed4013195</id>
        <sys_created_by>admin</sys_created_by>
        <sys_created_on>2024-04-17 09:07:30</sys_created_on>
        <sys_id>cc0cd0bec325021031f0171ed401317e</sys_id>
        <sys_mod_count>0</sys_mod_count>
        <sys_updated_by>admin</sys_updated_by>
        <sys_updated_on>2024-04-17 09:07:30</sys_updated_on>
        <table>var__m_sys_hub_flow_logic_input_af4e1945c3e232002841b63b12d3ae3e</table>
        <value/>
    </sys_element_mapping>
    <sys_hub_flow_logic_ext_input action="DELETE" query="model=e6bb987ec325021031f0171ed4013195"/>
    <sys_hub_input_scripts action="DELETE" query="instance=e6bb987ec325021031f0171ed4013195"/>
    <sys_hub_pill_compound action="DELETE" query="attached_to=787a943ac325021031f0171ed4013139"/>
    <sys_hub_flow_variable action="DELETE" query="model=787a943ac325021031f0171ed4013139"/>
    <sys_documentation action="DELETE" query="name=var__m_sys_hub_flow_input_787a943ac325021031f0171ed4013139^sys_idNOT IN2decd4fec325021031f0171ed40131a4,59ecd4fec325021031f0171ed4013190"/>
    <sys_documentation action="DELETE">
        <element>table_name</element>
        <help/>
        <hint/>
        <label>Table Name</label>
        <language>en</language>
        <name>var__m_sys_hub_flow_input_787a943ac325021031f0171ed4013139</name>
        <plural/>
        <sys_class_name>sys_documentation</sys_class_name>
        <sys_created_by>admin</sys_created_by>
        <sys_created_on>2024-04-17 09:11:25</sys_created_on>
        <sys_id>2decd4fec325021031f0171ed40131a4</sys_id>
        <sys_mod_count>0</sys_mod_count>
        <sys_name/>
        <sys_package display_value="NeedIt" source="x_58872_needit">6ead8e780f603200cd674f8ce1050ed1</sys_package>
        <sys_policy/>
        <sys_scope display_value="NeedIt">6ead8e780f603200cd674f8ce1050ed1</sys_scope>
        <sys_update_name/>
        <sys_updated_by>admin</sys_updated_by>
        <sys_updated_on>2024-04-17 09:11:25</sys_updated_on>
        <url/>
        <url_target/>
    </sys_documentation>
    <sys_documentation action="DELETE">
        <element>current</element>
        <help/>
        <hint/>
        <label>Record</label>
        <language>en</language>
        <name>var__m_sys_hub_flow_input_787a943ac325021031f0171ed4013139</name>
        <plural/>
        <sys_class_name>sys_documentation</sys_class_name>
        <sys_created_by>admin</sys_created_by>
        <sys_created_on>2024-04-17 09:11:25</sys_created_on>
        <sys_id>59ecd4fec325021031f0171ed4013190</sys_id>
        <sys_mod_count>0</sys_mod_count>
        <sys_name/>
        <sys_package display_value="NeedIt" source="x_58872_needit">6ead8e780f603200cd674f8ce1050ed1</sys_package>
        <sys_policy/>
        <sys_scope display_value="NeedIt">6ead8e780f603200cd674f8ce1050ed1</sys_scope>
        <sys_update_name/>
        <sys_updated_by>admin</sys_updated_by>
        <sys_updated_on>2024-04-17 09:11:25</sys_updated_on>
        <url/>
        <url_target/>
    </sys_documentation>
    <sys_choice action="DELETE" query="name=var__m_sys_hub_flow_input_787a943ac325021031f0171ed4013139"/>
    <sys_documentation action="DELETE" query="name=var__m_sys_hub_flow_output_787a943ac325021031f0171ed4013139"/>
    <sys_choice action="DELETE" query="name=var__m_sys_hub_flow_output_787a943ac325021031f0171ed4013139"/>
    <sys_flow_trigger_plan action="DELETE" query="plan_id=787a943ac325021031f0171ed4013139"/>
    <sys_flow_subflow_plan action="DELETE" query="plan_id=787a943ac325021031f0171ed4013139"/>
    <sys_update_version action="INSERT_OR_UPDATE">
        <action>DELETE</action>
        <application display_value="NeedIt">6ead8e780f603200cd674f8ce1050ed1</application>
        <file_path/>
        <instance_id>dddff9311bc1425432182f8dee4bcb45</instance_id>
        <instance_name>dev247061</instance_name>
        <name>sys_hub_flow_787a943ac325021031f0171ed4013139</name>
        <payload>&lt;?xml version="1.0" encoding="UTF-8"?&gt;&lt;record_update sys_domain="global" table="sys_hub_flow"&gt;&lt;sys_hub_flow action="INSERT_OR_UPDATE"&gt;&lt;access&gt;public&lt;/access&gt;&lt;acls/&gt;&lt;active&gt;false&lt;/active&gt;&lt;annotation/&gt;&lt;attributes&gt;labelCacheCleanUpExecuted=true&lt;/attributes&gt;&lt;authored_on_release_version&gt;25000&lt;/authored_on_release_version&gt;&lt;callable_by_client_api&gt;false&lt;/callable_by_client_api&gt;&lt;category/&gt;&lt;compiler_build/&gt;&lt;copied_from/&gt;&lt;copied_from_name/&gt;&lt;description&gt;Steps to approve and fulfill NeedIt requests.&lt;/description&gt;&lt;flow_priority&gt;MEDIUM&lt;/flow_priority&gt;&lt;generation_source/&gt;&lt;internal_name&gt;needit_fulfillment&lt;/internal_name&gt;&lt;label_cache&gt;[{"name":"Created_1.current","label":"Trigger - Record Created➛NeedIt Record","reference":"x_58872_needit_needit","reference_display":"NeedIt","type":"reference","base_type":"reference","parent_table_name":null,"column_name":null,"choices":null,"usedInstances":{"74cdd38d-6c6f-49fa-86d4-7a41eceab24a":["record"],"759a9d5a-d615-4b48-9a1e-cbc2f5c6d6c6":["record"]},"attributes":null},{"name":"Created_1.current.u_requested_for.manager","label":"Trigger - Record Created➛NeedIt Record➛Requested for➛Manager","reference":"sys_user","reference_display":"Manager","type":"reference","base_type":"reference","parent_table_name":null,"column_name":null,"choices":null,"usedInstances":{"74cdd38d-6c6f-49fa-86d4-7a41eceab24a":["approval_conditions"]},"attributes":null},{"name":"Created_1.current.u_requested_for","label":"Trigger - Record Created➛NeedIt Record➛Requested for","reference":"sys_user","reference_display":"Requested for","type":"reference","base_type":"reference","parent_table_name":null,"column_name":null,"choices":null,"usedInstances":{},"attributes":null},{"name":"74cdd38d-6c6f-49fa-86d4-7a41eceab24a.approval_state","label":"2 - Ask For Approval➛Approval State","reference":"","reference_display":"Approval State","type":"choice","base_type":"choice","parent_table_name":null,"column_name":null,"choices":null,"usedInstances":{"cdfddb15-2229-4aa3-b82e-123e9706b05a":["condition"]},"attributes":null},{"name":"759a9d5a-d615-4b48-9a1e-cbc2f5c6d6c6.record","label":"1 - Update Record➛NeedIt Record","reference":"x_58872_needit_needit","reference_display":"NeedIt","type":"reference","base_type":"reference","parent_table_name":null,"column_name":null,"choices":null,"usedInstances":{"e5375bff-84e4-4512-b72c-edb84fff1ad8":["record"],"232b8f15-7b91-4414-9cf3-db5cefa4115a":["record"]},"attributes":null}]&lt;/label_cache&gt;&lt;latest_snapshot/&gt;&lt;master_snapshot/&gt;&lt;name&gt;NeedIt Fulfillment&lt;/name&gt;&lt;natlang/&gt;&lt;outputs/&gt;&lt;pre_compiled&gt;false&lt;/pre_compiled&gt;&lt;remote_trigger_id/&gt;&lt;run_as&gt;user&lt;/run_as&gt;&lt;run_with_roles/&gt;&lt;sc_callable&gt;false&lt;/sc_callable&gt;&lt;show_draft_actions&gt;false&lt;/show_draft_actions&gt;&lt;show_triggered_flows&gt;false&lt;/show_triggered_flows&gt;&lt;status&gt;draft&lt;/status&gt;&lt;sys_class_name&gt;sys_hub_flow&lt;/sys_class_name&gt;&lt;sys_created_by&gt;admin&lt;/sys_created_by&gt;&lt;sys_created_on&gt;2024-04-17 09:00:43&lt;/sys_created_on&gt;&lt;sys_domain&gt;global&lt;/sys_domain&gt;&lt;sys_domain_path&gt;/&lt;/sys_domain_path&gt;&lt;sys_id&gt;787a943ac325021031f0171ed4013139&lt;/sys_id&gt;&lt;sys_mod_count&gt;32&lt;/sys_mod_count&gt;&lt;sys_name&gt;NeedIt Fulfillment&lt;/sys_name&gt;&lt;sys_overrides/&gt;&lt;sys_package display_value="NeedIt" source="x_58872_needit"&gt;6ead8e780f603200cd674f8ce1050ed1&lt;/sys_package&gt;&lt;sys_policy/&gt;&lt;sys_scope display_value="NeedIt"&gt;6ead8e780f603200cd674f8ce1050ed1&lt;/sys_scope&gt;&lt;sys_update_name&gt;sys_hub_flow_787a943ac325021031f0171ed4013139&lt;/sys_update_name&gt;&lt;sys_updated_by&gt;admin&lt;/sys_updated_by&gt;&lt;sys_updated_on&gt;2024-04-17 09:43:16&lt;/sys_updated_on&gt;&lt;type&gt;flow&lt;/type&gt;&lt;/sys_hub_flow&gt;&lt;sys_translated_text action="delete_multiple" query="documentkey=787a943ac325021031f0171ed4013139"/&gt;&lt;sys_variable_value action="delete_multiple" query="document_key=787a943ac325021031f0171ed4013139"/&gt;&lt;sys_hub_trigger_instance action="delete_multiple" query="flow=787a943ac325021031f0171ed4013139^sys_idNOT IN4baa503ec325021031f0171ed40131c5"/&gt;&lt;sys_hub_trigger_instance action="INSERT_OR_UPDATE"&gt;&lt;comment/&gt;&lt;display_text/&gt;&lt;flow display_value="NeedIt Fulfillment"&gt;787a943ac325021031f0171ed4013139&lt;/flow&gt;&lt;name&gt;Created&lt;/name&gt;&lt;remote_sys_id/&gt;&lt;sys_created_by&gt;admin&lt;/sys_created_by&gt;&lt;sys_created_on&gt;2024-04-17 09:01:42&lt;/sys_created_on&gt;&lt;sys_id&gt;4baa503ec325021031f0171ed40131c5&lt;/sys_id&gt;&lt;sys_mod_count&gt;3&lt;/sys_mod_count&gt;&lt;sys_scope/&gt;&lt;sys_updated_by&gt;admin&lt;/sys_updated_by&gt;&lt;sys_updated_on&gt;2024-04-17 09:20:47&lt;/sys_updated_on&gt;&lt;trigger_definition display_value="Created"&gt;798916a0c31322002841b63b12d3ae7c&lt;/trigger_definition&gt;&lt;trigger_inputs/&gt;&lt;trigger_outputs/&gt;&lt;trigger_type&gt;record_create&lt;/trigger_type&gt;&lt;/sys_hub_trigger_instance&gt;&lt;sys_variable_value action="delete_multiple" query="document_key=4baa503ec325021031f0171ed40131c5"/&gt;&lt;sys_variable_value action="INSERT_OR_UPDATE"&gt;&lt;document&gt;sys_hub_trigger_instance&lt;/document&gt;&lt;document_key&gt;4baa503ec325021031f0171ed40131c5&lt;/document_key&gt;&lt;order&gt;1&lt;/order&gt;&lt;sys_class_name&gt;sys_variable_value&lt;/sys_class_name&gt;&lt;sys_created_by&gt;admin&lt;/sys_created_by&gt;&lt;sys_created_on&gt;2024-04-17 09:01:42&lt;/sys_created_on&gt;&lt;sys_id&gt;43aa503ec325021031f0171ed40131c7&lt;/sys_id&gt;&lt;sys_mod_count&gt;0&lt;/sys_mod_count&gt;&lt;sys_updated_by&gt;admin&lt;/sys_updated_by&gt;&lt;sys_updated_on&gt;2024-04-17 09:01:42&lt;/sys_updated_on&gt;&lt;value&gt;x_58872_needit_needit&lt;/value&gt;&lt;variable display_value="Table"&gt;cfca92e0c31322002841b63b12d3ae00&lt;/variable&gt;&lt;/sys_variable_value&gt;&lt;sys_variable_value action="INSERT_OR_UPDATE"&gt;&lt;document&gt;sys_hub_trigger_instance&lt;/document&gt;&lt;document_key&gt;4baa503ec325021031f0171ed40131c5&lt;/document_key&gt;&lt;order&gt;100&lt;/order&gt;&lt;sys_class_name&gt;sys_variable_value&lt;/sys_class_name&gt;&lt;sys_created_by&gt;admin&lt;/sys_created_by&gt;&lt;sys_created_on&gt;2024-04-17 09:01:42&lt;/sys_created_on&gt;&lt;sys_id&gt;4baa503ec325021031f0171ed40131c6&lt;/sys_id&gt;&lt;sys_mod_count&gt;0&lt;/sys_mod_count&gt;&lt;sys_updated_by&gt;admin&lt;/sys_updated_by&gt;&lt;sys_updated_on&gt;2024-04-17 09:01:42&lt;/sys_updated_on&gt;&lt;value&gt;^EQ&lt;/value&gt;&lt;variable display_value="Condition"&gt;66aadea0c31322002841b63b12d3aebf&lt;/variable&gt;&lt;/sys_variable_value&gt;&lt;sys_hub_flow_stage action="delete_multiple" query="flow=787a943ac325021031f0171ed4013139"/&gt;&lt;sys_flow_cat_variable_model action="delete_multiple" query="id=787a943ac325021031f0171ed4013139^sys_idNOT IN747a943ac325021031f0171ed401313a"/&gt;&lt;sys_flow_cat_variable_model action="INSERT_OR_UPDATE"&gt;&lt;id&gt;787a943ac325021031f0171ed4013139&lt;/id&gt;&lt;name&gt;NeedIt Fulfillment&lt;/name&gt;&lt;sys_created_by&gt;admin&lt;/sys_created_by&gt;&lt;sys_created_on&gt;2024-04-17 09:00:43&lt;/sys_created_on&gt;&lt;sys_id&gt;747a943ac325021031f0171ed401313a&lt;/sys_id&gt;&lt;sys_mod_count&gt;0&lt;/sys_mod_count&gt;&lt;sys_scope/&gt;&lt;sys_updated_by&gt;admin&lt;/sys_updated_by&gt;&lt;sys_updated_on&gt;2024-04-17 09:00:43&lt;/sys_updated_on&gt;&lt;/sys_flow_cat_variable_model&gt;&lt;sys_flow_cat_variable action="delete_multiple" query="flow_catalog_model=747a943ac325021031f0171ed401313a"/&gt;&lt;sys_hub_flow_input action="delete_multiple" query="model=787a943ac325021031f0171ed4013139^sys_idNOT IN15ecd4fec325021031f0171ed4013189,a1ecd4fec325021031f0171ed4013194"/&gt;&lt;sys_hub_flow_input action="INSERT_OR_UPDATE"&gt;&lt;active&gt;true&lt;/active&gt;&lt;array&gt;false&lt;/array&gt;&lt;array_denormalized&gt;false&lt;/array_denormalized&gt;&lt;attributes&gt;element_mapping_provider=com.glide.flow_design.action.data.FlowDesignVariableMapper,uiType=document_id&lt;/attributes&gt;&lt;audit&gt;false&lt;/audit&gt;&lt;calculation&gt;&lt;![CDATA[(function calculatedFieldValue(current) {

	// Add your code here
	return '';  // return the calculated value

})(current);]]&gt;&lt;/calculation&gt;&lt;choice/&gt;&lt;choice_field/&gt;&lt;choice_table/&gt;&lt;column_label/&gt;&lt;comments/&gt;&lt;create_roles/&gt;&lt;default_value/&gt;&lt;defaultsort/&gt;&lt;delete_roles/&gt;&lt;dependent&gt;table_name&lt;/dependent&gt;&lt;dependent_on_field&gt;table_name&lt;/dependent_on_field&gt;&lt;display&gt;false&lt;/display&gt;&lt;dynamic_creation&gt;false&lt;/dynamic_creation&gt;&lt;dynamic_creation_script/&gt;&lt;dynamic_default_value/&gt;&lt;dynamic_ref_qual/&gt;&lt;element&gt;current&lt;/element&gt;&lt;element_reference&gt;false&lt;/element_reference&gt;&lt;foreign_database/&gt;&lt;formula/&gt;&lt;function_definition/&gt;&lt;function_field&gt;false&lt;/function_field&gt;&lt;help/&gt;&lt;hint/&gt;&lt;internal_type display_value=""&gt;document_id&lt;/internal_type&gt;&lt;label&gt;Record&lt;/label&gt;&lt;mandatory&gt;true&lt;/mandatory&gt;&lt;max_length&gt;200&lt;/max_length&gt;&lt;model display_value="NeedIt Fulfillment"&gt;787a943ac325021031f0171ed4013139&lt;/model&gt;&lt;model_id&gt;787a943ac325021031f0171ed4013139&lt;/model_id&gt;&lt;model_table&gt;sys_hub_flow&lt;/model_table&gt;&lt;name&gt;var__m_sys_hub_flow_input_787a943ac325021031f0171ed4013139&lt;/name&gt;&lt;next_element/&gt;&lt;order&gt;100&lt;/order&gt;&lt;primary&gt;false&lt;/primary&gt;&lt;read_only&gt;false&lt;/read_only&gt;&lt;read_roles/&gt;&lt;reference/&gt;&lt;reference_cascade_rule/&gt;&lt;reference_floats&gt;false&lt;/reference_floats&gt;&lt;reference_key/&gt;&lt;reference_qual/&gt;&lt;reference_qual_condition/&gt;&lt;reference_type/&gt;&lt;sizeclass/&gt;&lt;spell_check&gt;false&lt;/spell_check&gt;&lt;staged&gt;false&lt;/staged&gt;&lt;sys_class_name&gt;sys_hub_flow_input&lt;/sys_class_name&gt;&lt;sys_created_by&gt;admin&lt;/sys_created_by&gt;&lt;sys_created_on&gt;2024-04-17 09:11:25&lt;/sys_created_on&gt;&lt;sys_id&gt;15ecd4fec325021031f0171ed4013189&lt;/sys_id&gt;&lt;sys_mod_count&gt;0&lt;/sys_mod_count&gt;&lt;sys_name/&gt;&lt;sys_package/&gt;&lt;sys_policy/&gt;&lt;sys_scope display_value="NeedIt"&gt;6ead8e780f603200cd674f8ce1050ed1&lt;/sys_scope&gt;&lt;sys_update_name/&gt;&lt;sys_updated_by&gt;admin&lt;/sys_updated_by&gt;&lt;sys_updated_on&gt;2024-04-17 09:11:25&lt;/sys_updated_on&gt;&lt;table_reference&gt;false&lt;/table_reference&gt;&lt;text_index&gt;false&lt;/text_index&gt;&lt;unique&gt;false&lt;/unique&gt;&lt;use_dependent_field&gt;true&lt;/use_dependent_field&gt;&lt;use_dynamic_default&gt;false&lt;/use_dynamic_default&gt;&lt;use_reference_qualifier&gt;simple&lt;/use_reference_qualifier&gt;&lt;virtual&gt;false&lt;/virtual&gt;&lt;virtual_type&gt;script&lt;/virtual_type&gt;&lt;widget/&gt;&lt;write_roles/&gt;&lt;xml_view&gt;false&lt;/xml_view&gt;&lt;/sys_hub_flow_input&gt;&lt;sys_hub_action_input_action_instance action="delete_multiple" query="action_input=15ecd4fec325021031f0171ed4013189"/&gt;&lt;sys_hub_flow_input action="INSERT_OR_UPDATE"&gt;&lt;active&gt;true&lt;/active&gt;&lt;array&gt;false&lt;/array&gt;&lt;array_denormalized&gt;false&lt;/array_denormalized&gt;&lt;attributes&gt;element_mapping_provider=com.glide.flow_design.action.data.FlowDesignVariableMapper,test_input_hidden=true,uiType=table_name&lt;/attributes&gt;&lt;audit&gt;false&lt;/audit&gt;&lt;calculation&gt;&lt;![CDATA[(function calculatedFieldValue(current) {

	// Add your code here
	return '';  // return the calculated value

})(current);]]&gt;&lt;/calculation&gt;&lt;choice/&gt;&lt;choice_field/&gt;&lt;choice_table/&gt;&lt;column_label/&gt;&lt;comments/&gt;&lt;create_roles/&gt;&lt;default_value/&gt;&lt;defaultsort/&gt;&lt;delete_roles/&gt;&lt;dependent/&gt;&lt;dependent_on_field/&gt;&lt;display&gt;false&lt;/display&gt;&lt;dynamic_creation&gt;false&lt;/dynamic_creation&gt;&lt;dynamic_creation_script/&gt;&lt;dynamic_default_value/&gt;&lt;dynamic_ref_qual/&gt;&lt;element&gt;table_name&lt;/element&gt;&lt;element_reference&gt;false&lt;/element_reference&gt;&lt;foreign_database/&gt;&lt;formula/&gt;&lt;function_definition/&gt;&lt;function_field&gt;false&lt;/function_field&gt;&lt;help/&gt;&lt;hint/&gt;&lt;internal_type display_value=""&gt;table_name&lt;/internal_type&gt;&lt;label&gt;Table Name&lt;/label&gt;&lt;mandatory&gt;false&lt;/mandatory&gt;&lt;max_length&gt;200&lt;/max_length&gt;&lt;model display_value="NeedIt Fulfillment"&gt;787a943ac325021031f0171ed4013139&lt;/model&gt;&lt;model_id&gt;787a943ac325021031f0171ed4013139&lt;/model_id&gt;&lt;model_table&gt;sys_hub_flow&lt;/model_table&gt;&lt;name&gt;var__m_sys_hub_flow_input_787a943ac325021031f0171ed4013139&lt;/name&gt;&lt;next_element/&gt;&lt;order&gt;101&lt;/order&gt;&lt;primary&gt;false&lt;/primary&gt;&lt;read_only&gt;false&lt;/read_only&gt;&lt;read_roles/&gt;&lt;reference/&gt;&lt;reference_cascade_rule/&gt;&lt;reference_floats&gt;false&lt;/reference_floats&gt;&lt;reference_key/&gt;&lt;reference_qual/&gt;&lt;reference_qual_condition/&gt;&lt;reference_type/&gt;&lt;sizeclass/&gt;&lt;spell_check&gt;false&lt;/spell_check&gt;&lt;staged&gt;false&lt;/staged&gt;&lt;sys_class_name&gt;sys_hub_flow_input&lt;/sys_class_name&gt;&lt;sys_created_by&gt;admin&lt;/sys_created_by&gt;&lt;sys_created_on&gt;2024-04-17 09:11:25&lt;/sys_created_on&gt;&lt;sys_id&gt;a1ecd4fec325021031f0171ed4013194&lt;/sys_id&gt;&lt;sys_mod_count&gt;0&lt;/sys_mod_count&gt;&lt;sys_name/&gt;&lt;sys_package/&gt;&lt;sys_policy/&gt;&lt;sys_scope display_value="NeedIt"&gt;6ead8e780f603200cd674f8ce1050ed1&lt;/sys_scope&gt;&lt;sys_update_name/&gt;&lt;sys_updated_by&gt;admin&lt;/sys_updated_by&gt;&lt;sys_updated_on&gt;2024-04-17 09:11:25&lt;/sys_updated_on&gt;&lt;table_reference&gt;false&lt;/table_reference&gt;&lt;text_index&gt;false&lt;/text_index&gt;&lt;unique&gt;false&lt;/unique&gt;&lt;use_dependent_field&gt;false&lt;/use_dependent_field&gt;&lt;use_dynamic_default&gt;false&lt;/use_dynamic_default&gt;&lt;use_reference_qualifier&gt;simple&lt;/use_reference_qualifier&gt;&lt;virtual&gt;false&lt;/virtual&gt;&lt;virtual_type&gt;script&lt;/virtual_type&gt;&lt;widget/&gt;&lt;write_roles/&gt;&lt;xml_view&gt;false&lt;/xml_view&gt;&lt;/sys_hub_flow_input&gt;&lt;sys_hub_action_input_action_instance action="delete_multiple" query="action_input=a1ecd4fec325021031f0171ed4013194"/&gt;&lt;sys_hub_flow_output action="delete_multiple" query="model=787a943ac325021031f0171ed4013139"/&gt;&lt;sys_hub_alias_mapping action="delete_multiple" query="source_id=787a943ac325021031f0171ed4013139"/&gt;&lt;sys_hub_action_instance action="delete_multiple" query="flow=787a943ac325021031f0171ed4013139^sys_idNOT IN551c18fac325021031f0171ed40131c1,5c3bd0bac325021031f0171ed40131de,8a8c507ec325021031f0171ed4013165,a9bad43ec325021031f0171ed40131fc"/&gt;&lt;sys_hub_action_instance action="INSERT_OR_UPDATE"&gt;&lt;action_inputs/&gt;&lt;action_inputs/&gt;&lt;action_type display_value="Update Record"&gt;f9d01dd2c31332002841b63b12d3aea1&lt;/action_type&gt;&lt;action_type_parent/&gt;&lt;attributes/&gt;&lt;comment&gt;Update NeedIt State to Approved&lt;/comment&gt;&lt;compiled_snapshot/&gt;&lt;display_text/&gt;&lt;flow display_value="NeedIt Fulfillment"&gt;787a943ac325021031f0171ed4013139&lt;/flow&gt;&lt;generation_source/&gt;&lt;order&gt;4&lt;/order&gt;&lt;parent_ui_id&gt;cdfddb15-2229-4aa3-b82e-123e9706b05a&lt;/parent_ui_id&gt;&lt;sys_class_name&gt;sys_hub_action_instance&lt;/sys_class_name&gt;&lt;sys_created_by&gt;admin&lt;/sys_created_by&gt;&lt;sys_created_on&gt;2024-04-17 09:07:51&lt;/sys_created_on&gt;&lt;sys_id&gt;551c18fac325021031f0171ed40131c1&lt;/sys_id&gt;&lt;sys_mod_count&gt;6&lt;/sys_mod_count&gt;&lt;sys_scope display_value="NeedIt"&gt;6ead8e780f603200cd674f8ce1050ed1&lt;/sys_scope&gt;&lt;sys_updated_by&gt;admin&lt;/sys_updated_by&gt;&lt;sys_updated_on&gt;2024-04-17 09:09:00&lt;/sys_updated_on&gt;&lt;ui_id&gt;232b8f15-7b91-4414-9cf3-db5cefa4115a&lt;/ui_id&gt;&lt;/sys_hub_action_instance&gt;&lt;sys_variable_value action="delete_multiple" query="document_key=551c18fac325021031f0171ed40131c1"/&gt;&lt;sys_variable_value action="INSERT_OR_UPDATE"&gt;&lt;document&gt;sys_hub_action_instance&lt;/document&gt;&lt;document_key&gt;551c18fac325021031f0171ed40131c1&lt;/document_key&gt;&lt;order&gt;50&lt;/order&gt;&lt;sys_class_name&gt;sys_variable_value&lt;/sys_class_name&gt;&lt;sys_created_by&gt;admin&lt;/sys_created_by&gt;&lt;sys_created_on&gt;2024-04-17 09:09:00&lt;/sys_created_on&gt;&lt;sys_id&gt;8a5c54bec325021031f0171ed401310d&lt;/sys_id&gt;&lt;sys_mod_count&gt;0&lt;/sys_mod_count&gt;&lt;sys_updated_by&gt;admin&lt;/sys_updated_by&gt;&lt;sys_updated_on&gt;2024-04-17 09:09:00&lt;/sys_updated_on&gt;&lt;value&gt;x_58872_needit_needit&lt;/value&gt;&lt;variable display_value="Table"&gt;b5d01916c31332002841b63b12d3aec9&lt;/variable&gt;&lt;/sys_variable_value&gt;&lt;sys_variable_value action="INSERT_OR_UPDATE"&gt;&lt;document&gt;sys_hub_action_instance&lt;/document&gt;&lt;document_key&gt;551c18fac325021031f0171ed40131c1&lt;/document_key&gt;&lt;order&gt;100&lt;/order&gt;&lt;sys_class_name&gt;sys_variable_value&lt;/sys_class_name&gt;&lt;sys_created_by&gt;admin&lt;/sys_created_by&gt;&lt;sys_created_on&gt;2024-04-17 09:09:00&lt;/sys_created_on&gt;&lt;sys_id&gt;c65c54bec325021031f0171ed401310d&lt;/sys_id&gt;&lt;sys_mod_count&gt;0&lt;/sys_mod_count&gt;&lt;sys_updated_by&gt;admin&lt;/sys_updated_by&gt;&lt;sys_updated_on&gt;2024-04-17 09:09:00&lt;/sys_updated_on&gt;&lt;value&gt;state=15&lt;/value&gt;&lt;variable display_value="Fields"&gt;02d01916c31332002841b63b12d3aeee&lt;/variable&gt;&lt;/sys_variable_value&gt;&lt;sys_element_mapping action="delete_multiple" query="id=551c18fac325021031f0171ed40131c1"/&gt;&lt;sys_element_mapping action="INSERT_OR_UPDATE"&gt;&lt;field&gt;record&lt;/field&gt;&lt;id&gt;551c18fac325021031f0171ed40131c1&lt;/id&gt;&lt;sys_created_by&gt;admin&lt;/sys_created_by&gt;&lt;sys_created_on&gt;2024-04-17 09:09:00&lt;/sys_created_on&gt;&lt;sys_id&gt;465c54bec325021031f0171ed401310d&lt;/sys_id&gt;&lt;sys_mod_count&gt;0&lt;/sys_mod_count&gt;&lt;sys_updated_by&gt;admin&lt;/sys_updated_by&gt;&lt;sys_updated_on&gt;2024-04-17 09:09:00&lt;/sys_updated_on&gt;&lt;table&gt;var__m_sys_hub_action_input_f9d01dd2c31332002841b63b12d3aea1&lt;/table&gt;&lt;value&gt;{{759a9d5a-d615-4b48-9a1e-cbc2f5c6d6c6.record}}&lt;/value&gt;&lt;/sys_element_mapping&gt;&lt;sys_element_mapping action="INSERT_OR_UPDATE"&gt;&lt;field&gt;table_name&lt;/field&gt;&lt;id&gt;551c18fac325021031f0171ed40131c1&lt;/id&gt;&lt;sys_created_by&gt;admin&lt;/sys_created_by&gt;&lt;sys_created_on&gt;2024-04-17 09:09:00&lt;/sys_created_on&gt;&lt;sys_id&gt;ce5c54bec325021031f0171ed401310c&lt;/sys_id&gt;&lt;sys_mod_count&gt;0&lt;/sys_mod_count&gt;&lt;sys_updated_by&gt;admin&lt;/sys_updated_by&gt;&lt;sys_updated_on&gt;2024-04-17 09:09:00&lt;/sys_updated_on&gt;&lt;table&gt;var__m_sys_hub_action_input_f9d01dd2c31332002841b63b12d3aea1&lt;/table&gt;&lt;value/&gt;&lt;/sys_element_mapping&gt;&lt;sys_element_mapping action="INSERT_OR_UPDATE"&gt;&lt;field&gt;values&lt;/field&gt;&lt;id&gt;551c18fac325021031f0171ed40131c1&lt;/id&gt;&lt;sys_created_by&gt;admin&lt;/sys_created_by&gt;&lt;sys_created_on&gt;2024-04-17 09:09:00&lt;/sys_created_on&gt;&lt;sys_id&gt;825c54bec325021031f0171ed401310d&lt;/sys_id&gt;&lt;sys_mod_count&gt;0&lt;/sys_mod_count&gt;&lt;sys_updated_by&gt;admin&lt;/sys_updated_by&gt;&lt;sys_updated_on&gt;2024-04-17 09:09:00&lt;/sys_updated_on&gt;&lt;table&gt;var__m_sys_hub_action_input_f9d01dd2c31332002841b63b12d3aea1&lt;/table&gt;&lt;value/&gt;&lt;/sys_element_mapping&gt;&lt;sys_hub_input_scripts action="delete_multiple" query="instance=551c18fac325021031f0171ed40131c1"/&gt;&lt;sys_hub_alias_mapping action="delete_multiple" query="source_id=551c18fac325021031f0171ed40131c1"/&gt;&lt;sys_hub_action_instance action="INSERT_OR_UPDATE"&gt;&lt;action_inputs/&gt;&lt;action_inputs/&gt;&lt;action_type display_value="Ask For Approval"&gt;f8f2e9920b10030085c083eb37673abd&lt;/action_type&gt;&lt;action_type_parent/&gt;&lt;attributes/&gt;&lt;comment&gt;Get approval from Requested for's Manager&lt;/comment&gt;&lt;compiled_snapshot/&gt;&lt;display_text/&gt;&lt;flow display_value="NeedIt Fulfillment"&gt;787a943ac325021031f0171ed4013139&lt;/flow&gt;&lt;generation_source/&gt;&lt;order&gt;2&lt;/order&gt;&lt;parent_ui_id/&gt;&lt;sys_class_name&gt;sys_hub_action_instance&lt;/sys_class_name&gt;&lt;sys_created_by&gt;admin&lt;/sys_created_by&gt;&lt;sys_created_on&gt;2024-04-17 09:03:57&lt;/sys_created_on&gt;&lt;sys_id&gt;5c3bd0bac325021031f0171ed40131de&lt;/sys_id&gt;&lt;sys_mod_count&gt;4&lt;/sys_mod_count&gt;&lt;sys_scope display_value="NeedIt"&gt;6ead8e780f603200cd674f8ce1050ed1&lt;/sys_scope&gt;&lt;sys_updated_by&gt;admin&lt;/sys_updated_by&gt;&lt;sys_updated_on&gt;2024-04-17 09:06:07&lt;/sys_updated_on&gt;&lt;ui_id&gt;74cdd38d-6c6f-49fa-86d4-7a41eceab24a&lt;/ui_id&gt;&lt;/sys_hub_action_instance&gt;&lt;sys_variable_value action="delete_multiple" query="document_key=5c3bd0bac325021031f0171ed40131de"/&gt;&lt;sys_variable_value action="INSERT_OR_UPDATE"&gt;&lt;document&gt;sys_hub_action_instance&lt;/document&gt;&lt;document_key&gt;5c3bd0bac325021031f0171ed40131de&lt;/document_key&gt;&lt;order&gt;5&lt;/order&gt;&lt;sys_class_name&gt;sys_variable_value&lt;/sys_class_name&gt;&lt;sys_created_by&gt;admin&lt;/sys_created_by&gt;&lt;sys_created_on&gt;2024-04-17 09:06:07&lt;/sys_created_on&gt;&lt;sys_id&gt;37ab1c7ec325021031f0171ed401317b&lt;/sys_id&gt;&lt;sys_mod_count&gt;0&lt;/sys_mod_count&gt;&lt;sys_updated_by&gt;admin&lt;/sys_updated_by&gt;&lt;sys_updated_on&gt;2024-04-17 09:06:07&lt;/sys_updated_on&gt;&lt;value/&gt;&lt;variable display_value="Due Date"&gt;c5f2e9920b10030085c083eb37673af9&lt;/variable&gt;&lt;/sys_variable_value&gt;&lt;sys_variable_value action="INSERT_OR_UPDATE"&gt;&lt;document&gt;sys_hub_action_instance&lt;/document&gt;&lt;document_key&gt;5c3bd0bac325021031f0171ed40131de&lt;/document_key&gt;&lt;order&gt;3&lt;/order&gt;&lt;sys_class_name&gt;sys_variable_value&lt;/sys_class_name&gt;&lt;sys_created_by&gt;admin&lt;/sys_created_by&gt;&lt;sys_created_on&gt;2024-04-17 09:06:07&lt;/sys_created_on&gt;&lt;sys_id&gt;73ab1c7ec325021031f0171ed401317b&lt;/sys_id&gt;&lt;sys_mod_count&gt;0&lt;/sys_mod_count&gt;&lt;sys_updated_by&gt;admin&lt;/sys_updated_by&gt;&lt;sys_updated_on&gt;2024-04-17 09:06:07&lt;/sys_updated_on&gt;&lt;value&gt;approval_history&lt;/value&gt;&lt;variable display_value="Journal Field"&gt;c1f2e9920b10030085c083eb37673ae3&lt;/variable&gt;&lt;/sys_variable_value&gt;&lt;sys_variable_value action="INSERT_OR_UPDATE"&gt;&lt;document&gt;sys_hub_action_instance&lt;/document&gt;&lt;document_key&gt;5c3bd0bac325021031f0171ed40131de&lt;/document_key&gt;&lt;order&gt;2&lt;/order&gt;&lt;sys_class_name&gt;sys_variable_value&lt;/sys_class_name&gt;&lt;sys_created_by&gt;admin&lt;/sys_created_by&gt;&lt;sys_created_on&gt;2024-04-17 09:06:07&lt;/sys_created_on&gt;&lt;sys_id&gt;bfab1c7ec325021031f0171ed401317a&lt;/sys_id&gt;&lt;sys_mod_count&gt;0&lt;/sys_mod_count&gt;&lt;sys_updated_by&gt;admin&lt;/sys_updated_by&gt;&lt;sys_updated_on&gt;2024-04-17 09:06:07&lt;/sys_updated_on&gt;&lt;value&gt;approval&lt;/value&gt;&lt;variable display_value="Approval Field"&gt;01f2e9920b10030085c083eb37673ad8&lt;/variable&gt;&lt;/sys_variable_value&gt;&lt;sys_variable_value action="INSERT_OR_UPDATE"&gt;&lt;document&gt;sys_hub_action_instance&lt;/document&gt;&lt;document_key&gt;5c3bd0bac325021031f0171ed40131de&lt;/document_key&gt;&lt;order&gt;1&lt;/order&gt;&lt;sys_class_name&gt;sys_variable_value&lt;/sys_class_name&gt;&lt;sys_created_by&gt;admin&lt;/sys_created_by&gt;&lt;sys_created_on&gt;2024-04-17 09:06:07&lt;/sys_created_on&gt;&lt;sys_id&gt;f7ab1c7ec325021031f0171ed401317b&lt;/sys_id&gt;&lt;sys_mod_count&gt;0&lt;/sys_mod_count&gt;&lt;sys_updated_by&gt;admin&lt;/sys_updated_by&gt;&lt;sys_updated_on&gt;2024-04-17 09:06:07&lt;/sys_updated_on&gt;&lt;value&gt;x_58872_needit_needit&lt;/value&gt;&lt;variable display_value="Table"&gt;bcf2e9920b10030085c083eb37673acc&lt;/variable&gt;&lt;/sys_variable_value&gt;&lt;sys_element_mapping action="delete_multiple" query="id=5c3bd0bac325021031f0171ed40131de"/&gt;&lt;sys_element_mapping action="INSERT_OR_UPDATE"&gt;&lt;field&gt;approval_conditions&lt;/field&gt;&lt;id&gt;5c3bd0bac325021031f0171ed40131de&lt;/id&gt;&lt;sys_created_by&gt;admin&lt;/sys_created_by&gt;&lt;sys_created_on&gt;2024-04-17 09:06:07&lt;/sys_created_on&gt;&lt;sys_id&gt;7bab1c7ec325021031f0171ed401317a&lt;/sys_id&gt;&lt;sys_mod_count&gt;0&lt;/sys_mod_count&gt;&lt;sys_updated_by&gt;admin&lt;/sys_updated_by&gt;&lt;sys_updated_on&gt;2024-04-17 09:06:07&lt;/sys_updated_on&gt;&lt;table&gt;var__m_sys_hub_action_input_f8f2e9920b10030085c083eb37673abd&lt;/table&gt;&lt;value&gt;ApprovesRejectsAnyU[{{Created_1.current.u_requested_for.manager}}]&lt;/value&gt;&lt;/sys_element_mapping&gt;&lt;sys_element_mapping action="INSERT_OR_UPDATE"&gt;&lt;field&gt;approval_field&lt;/field&gt;&lt;id&gt;5c3bd0bac325021031f0171ed40131de&lt;/id&gt;&lt;sys_created_by&gt;admin&lt;/sys_created_by&gt;&lt;sys_created_on&gt;2024-04-17 09:06:07&lt;/sys_created_on&gt;&lt;sys_id&gt;bbab503ec325021031f0171ed40131cd&lt;/sys_id&gt;&lt;sys_mod_count&gt;0&lt;/sys_mod_count&gt;&lt;sys_updated_by&gt;admin&lt;/sys_updated_by&gt;&lt;sys_updated_on&gt;2024-04-17 09:06:07&lt;/sys_updated_on&gt;&lt;table&gt;var__m_sys_hub_action_input_f8f2e9920b10030085c083eb37673abd&lt;/table&gt;&lt;value/&gt;&lt;/sys_element_mapping&gt;&lt;sys_element_mapping action="INSERT_OR_UPDATE"&gt;&lt;field&gt;due_date&lt;/field&gt;&lt;id&gt;5c3bd0bac325021031f0171ed40131de&lt;/id&gt;&lt;sys_created_by&gt;admin&lt;/sys_created_by&gt;&lt;sys_created_on&gt;2024-04-17 09:06:07&lt;/sys_created_on&gt;&lt;sys_id&gt;f3ab503ec325021031f0171ed40131ce&lt;/sys_id&gt;&lt;sys_mod_count&gt;0&lt;/sys_mod_count&gt;&lt;sys_updated_by&gt;admin&lt;/sys_updated_by&gt;&lt;sys_updated_on&gt;2024-04-17 09:06:07&lt;/sys_updated_on&gt;&lt;table&gt;var__m_sys_hub_action_input_f8f2e9920b10030085c083eb37673abd&lt;/table&gt;&lt;value&gt;{"action":"none","date_type":"actual","date":"{{}}","duration":1,"duration_type":"days","schedule":"","schedule_label":""}&lt;/value&gt;&lt;/sys_element_mapping&gt;&lt;sys_element_mapping action="INSERT_OR_UPDATE"&gt;&lt;field&gt;journal_field&lt;/field&gt;&lt;id&gt;5c3bd0bac325021031f0171ed40131de&lt;/id&gt;&lt;sys_created_by&gt;admin&lt;/sys_created_by&gt;&lt;sys_created_on&gt;2024-04-17 09:06:07&lt;/sys_created_on&gt;&lt;sys_id&gt;7fab503ec325021031f0171ed40131cd&lt;/sys_id&gt;&lt;sys_mod_count&gt;0&lt;/sys_mod_count&gt;&lt;sys_updated_by&gt;admin&lt;/sys_updated_by&gt;&lt;sys_updated_on&gt;2024-04-17 09:06:07&lt;/sys_updated_on&gt;&lt;table&gt;var__m_sys_hub_action_input_f8f2e9920b10030085c083eb37673abd&lt;/table&gt;&lt;value/&gt;&lt;/sys_element_mapping&gt;&lt;sys_element_mapping action="INSERT_OR_UPDATE"&gt;&lt;field&gt;record&lt;/field&gt;&lt;id&gt;5c3bd0bac325021031f0171ed40131de&lt;/id&gt;&lt;sys_created_by&gt;admin&lt;/sys_created_by&gt;&lt;sys_created_on&gt;2024-04-17 09:06:07&lt;/sys_created_on&gt;&lt;sys_id&gt;33ab503ec325021031f0171ed40131ce&lt;/sys_id&gt;&lt;sys_mod_count&gt;0&lt;/sys_mod_count&gt;&lt;sys_updated_by&gt;admin&lt;/sys_updated_by&gt;&lt;sys_updated_on&gt;2024-04-17 09:06:07&lt;/sys_updated_on&gt;&lt;table&gt;var__m_sys_hub_action_input_f8f2e9920b10030085c083eb37673abd&lt;/table&gt;&lt;value&gt;{{Created_1.current}}&lt;/value&gt;&lt;/sys_element_mapping&gt;&lt;sys_element_mapping action="INSERT_OR_UPDATE"&gt;&lt;field&gt;table&lt;/field&gt;&lt;id&gt;5c3bd0bac325021031f0171ed40131de&lt;/id&gt;&lt;sys_created_by&gt;admin&lt;/sys_created_by&gt;&lt;sys_created_on&gt;2024-04-17 09:06:07&lt;/sys_created_on&gt;&lt;sys_id&gt;3fab1c7ec325021031f0171ed401317a&lt;/sys_id&gt;&lt;sys_mod_count&gt;0&lt;/sys_mod_count&gt;&lt;sys_updated_by&gt;admin&lt;/sys_updated_by&gt;&lt;sys_updated_on&gt;2024-04-17 09:06:07&lt;/sys_updated_on&gt;&lt;table&gt;var__m_sys_hub_action_input_f8f2e9920b10030085c083eb37673abd&lt;/table&gt;&lt;value/&gt;&lt;/sys_element_mapping&gt;&lt;sys_hub_input_scripts action="delete_multiple" query="instance=5c3bd0bac325021031f0171ed40131de"/&gt;&lt;sys_hub_alias_mapping action="delete_multiple" query="source_id=5c3bd0bac325021031f0171ed40131de"/&gt;&lt;sys_hub_action_instance action="INSERT_OR_UPDATE"&gt;&lt;action_inputs/&gt;&lt;action_inputs/&gt;&lt;action_type display_value="Update Record"&gt;f9d01dd2c31332002841b63b12d3aea1&lt;/action_type&gt;&lt;action_type_parent/&gt;&lt;attributes/&gt;&lt;comment&gt;Update NeedIt State to Closed Complete&lt;/comment&gt;&lt;compiled_snapshot/&gt;&lt;display_text/&gt;&lt;flow display_value="NeedIt Fulfillment"&gt;787a943ac325021031f0171ed4013139&lt;/flow&gt;&lt;generation_source/&gt;&lt;order&gt;6&lt;/order&gt;&lt;parent_ui_id&gt;b4a2010b-b985-4530-a999-29fa931b3ad2&lt;/parent_ui_id&gt;&lt;sys_class_name&gt;sys_hub_action_instance&lt;/sys_class_name&gt;&lt;sys_created_by&gt;admin&lt;/sys_created_by&gt;&lt;sys_created_on&gt;2024-04-17 09:09:49&lt;/sys_created_on&gt;&lt;sys_id&gt;8a8c507ec325021031f0171ed4013165&lt;/sys_id&gt;&lt;sys_mod_count&gt;6&lt;/sys_mod_count&gt;&lt;sys_scope display_value="NeedIt"&gt;6ead8e780f603200cd674f8ce1050ed1&lt;/sys_scope&gt;&lt;sys_updated_by&gt;admin&lt;/sys_updated_by&gt;&lt;sys_updated_on&gt;2024-04-17 09:10:14&lt;/sys_updated_on&gt;&lt;ui_id&gt;e5375bff-84e4-4512-b72c-edb84fff1ad8&lt;/ui_id&gt;&lt;/sys_hub_action_instance&gt;&lt;sys_variable_value action="delete_multiple" query="document_key=8a8c507ec325021031f0171ed4013165"/&gt;&lt;sys_variable_value action="INSERT_OR_UPDATE"&gt;&lt;document&gt;sys_hub_action_instance&lt;/document&gt;&lt;document_key&gt;8a8c507ec325021031f0171ed4013165&lt;/document_key&gt;&lt;order&gt;100&lt;/order&gt;&lt;sys_class_name&gt;sys_variable_value&lt;/sys_class_name&gt;&lt;sys_created_by&gt;admin&lt;/sys_created_by&gt;&lt;sys_created_on&gt;2024-04-17 09:10:12&lt;/sys_created_on&gt;&lt;sys_id&gt;3b9cd0bec325021031f0171ed40131b5&lt;/sys_id&gt;&lt;sys_mod_count&gt;0&lt;/sys_mod_count&gt;&lt;sys_updated_by&gt;admin&lt;/sys_updated_by&gt;&lt;sys_updated_on&gt;2024-04-17 09:10:12&lt;/sys_updated_on&gt;&lt;value&gt;state=3&lt;/value&gt;&lt;variable display_value="Fields"&gt;02d01916c31332002841b63b12d3aeee&lt;/variable&gt;&lt;/sys_variable_value&gt;&lt;sys_variable_value action="INSERT_OR_UPDATE"&gt;&lt;document&gt;sys_hub_action_instance&lt;/document&gt;&lt;document_key&gt;8a8c507ec325021031f0171ed4013165&lt;/document_key&gt;&lt;order&gt;50&lt;/order&gt;&lt;sys_class_name&gt;sys_variable_value&lt;/sys_class_name&gt;&lt;sys_created_by&gt;admin&lt;/sys_created_by&gt;&lt;sys_created_on&gt;2024-04-17 09:10:13&lt;/sys_created_on&gt;&lt;sys_id&gt;fb9cd0bec325021031f0171ed40131b5&lt;/sys_id&gt;&lt;sys_mod_count&gt;0&lt;/sys_mod_count&gt;&lt;sys_updated_by&gt;admin&lt;/sys_updated_by&gt;&lt;sys_updated_on&gt;2024-04-17 09:10:13&lt;/sys_updated_on&gt;&lt;value&gt;x_58872_needit_needit&lt;/value&gt;&lt;variable display_value="Table"&gt;b5d01916c31332002841b63b12d3aec9&lt;/variable&gt;&lt;/sys_variable_value&gt;&lt;sys_element_mapping action="delete_multiple" query="id=8a8c507ec325021031f0171ed4013165"/&gt;&lt;sys_element_mapping action="INSERT_OR_UPDATE"&gt;&lt;field&gt;record&lt;/field&gt;&lt;id&gt;8a8c507ec325021031f0171ed4013165&lt;/id&gt;&lt;sys_created_by&gt;admin&lt;/sys_created_by&gt;&lt;sys_created_on&gt;2024-04-17 09:10:12&lt;/sys_created_on&gt;&lt;sys_id&gt;b79cd0bec325021031f0171ed40131b5&lt;/sys_id&gt;&lt;sys_mod_count&gt;0&lt;/sys_mod_count&gt;&lt;sys_updated_by&gt;admin&lt;/sys_updated_by&gt;&lt;sys_updated_on&gt;2024-04-17 09:10:12&lt;/sys_updated_on&gt;&lt;table&gt;var__m_sys_hub_action_input_f9d01dd2c31332002841b63b12d3aea1&lt;/table&gt;&lt;value&gt;{{759a9d5a-d615-4b48-9a1e-cbc2f5c6d6c6.record}}&lt;/value&gt;&lt;/sys_element_mapping&gt;&lt;sys_element_mapping action="INSERT_OR_UPDATE"&gt;&lt;field&gt;table_name&lt;/field&gt;&lt;id&gt;8a8c507ec325021031f0171ed4013165&lt;/id&gt;&lt;sys_created_by&gt;admin&lt;/sys_created_by&gt;&lt;sys_created_on&gt;2024-04-17 09:10:12&lt;/sys_created_on&gt;&lt;sys_id&gt;339cd0bec325021031f0171ed40131b5&lt;/sys_id&gt;&lt;sys_mod_count&gt;0&lt;/sys_mod_count&gt;&lt;sys_updated_by&gt;admin&lt;/sys_updated_by&gt;&lt;sys_updated_on&gt;2024-04-17 09:10:12&lt;/sys_updated_on&gt;&lt;table&gt;var__m_sys_hub_action_input_f9d01dd2c31332002841b63b12d3aea1&lt;/table&gt;&lt;value/&gt;&lt;/sys_element_mapping&gt;&lt;sys_element_mapping action="INSERT_OR_UPDATE"&gt;&lt;field&gt;values&lt;/field&gt;&lt;id&gt;8a8c507ec325021031f0171ed4013165&lt;/id&gt;&lt;sys_created_by&gt;admin&lt;/sys_created_by&gt;&lt;sys_created_on&gt;2024-04-17 09:10:12&lt;/sys_created_on&gt;&lt;sys_id&gt;f39cd0bec325021031f0171ed40131b5&lt;/sys_id&gt;&lt;sys_mod_count&gt;0&lt;/sys_mod_count&gt;&lt;sys_updated_by&gt;admin&lt;/sys_updated_by&gt;&lt;sys_updated_on&gt;2024-04-17 09:10:12&lt;/sys_updated_on&gt;&lt;table&gt;var__m_sys_hub_action_input_f9d01dd2c31332002841b63b12d3aea1&lt;/table&gt;&lt;value/&gt;&lt;/sys_element_mapping&gt;&lt;sys_hub_input_scripts action="delete_multiple" query="instance=8a8c507ec325021031f0171ed4013165"/&gt;&lt;sys_hub_alias_mapping action="delete_multiple" query="source_id=8a8c507ec325021031f0171ed4013165"/&gt;&lt;sys_hub_action_instance action="INSERT_OR_UPDATE"&gt;&lt;action_inputs/&gt;&lt;action_inputs/&gt;&lt;action_type display_value="Update Record"&gt;f9d01dd2c31332002841b63b12d3aea1&lt;/action_type&gt;&lt;action_type_parent/&gt;&lt;attributes/&gt;&lt;comment&gt;Set State to Awaiting Approval&lt;/comment&gt;&lt;compiled_snapshot/&gt;&lt;display_text/&gt;&lt;flow display_value="NeedIt Fulfillment"&gt;787a943ac325021031f0171ed4013139&lt;/flow&gt;&lt;generation_source/&gt;&lt;order&gt;1&lt;/order&gt;&lt;parent_ui_id/&gt;&lt;sys_class_name&gt;sys_hub_action_instance&lt;/sys_class_name&gt;&lt;sys_created_by&gt;admin&lt;/sys_created_by&gt;&lt;sys_created_on&gt;2024-04-17 09:01:51&lt;/sys_created_on&gt;&lt;sys_id&gt;a9bad43ec325021031f0171ed40131fc&lt;/sys_id&gt;&lt;sys_mod_count&gt;18&lt;/sys_mod_count&gt;&lt;sys_scope display_value="NeedIt"&gt;6ead8e780f603200cd674f8ce1050ed1&lt;/sys_scope&gt;&lt;sys_updated_by&gt;admin&lt;/sys_updated_by&gt;&lt;sys_updated_on&gt;2024-04-17 09:43:06&lt;/sys_updated_on&gt;&lt;ui_id&gt;759a9d5a-d615-4b48-9a1e-cbc2f5c6d6c6&lt;/ui_id&gt;&lt;/sys_hub_action_instance&gt;&lt;sys_variable_value action="delete_multiple" query="document_key=a9bad43ec325021031f0171ed40131fc"/&gt;&lt;sys_variable_value action="INSERT_OR_UPDATE"&gt;&lt;document&gt;sys_hub_action_instance&lt;/document&gt;&lt;document_key&gt;a9bad43ec325021031f0171ed40131fc&lt;/document_key&gt;&lt;order&gt;50&lt;/order&gt;&lt;sys_class_name&gt;sys_variable_value&lt;/sys_class_name&gt;&lt;sys_created_by&gt;admin&lt;/sys_created_by&gt;&lt;sys_created_on&gt;2024-04-17 09:02:13&lt;/sys_created_on&gt;&lt;sys_id&gt;b6ca583ec325021031f0171ed40131fa&lt;/sys_id&gt;&lt;sys_mod_count&gt;0&lt;/sys_mod_count&gt;&lt;sys_updated_by&gt;admin&lt;/sys_updated_by&gt;&lt;sys_updated_on&gt;2024-04-17 09:02:13&lt;/sys_updated_on&gt;&lt;value&gt;x_58872_needit_needit&lt;/value&gt;&lt;variable display_value="Table"&gt;b5d01916c31332002841b63b12d3aec9&lt;/variable&gt;&lt;/sys_variable_value&gt;&lt;sys_variable_value action="INSERT_OR_UPDATE"&gt;&lt;document&gt;sys_hub_action_instance&lt;/document&gt;&lt;document_key&gt;a9bad43ec325021031f0171ed40131fc&lt;/document_key&gt;&lt;order&gt;100&lt;/order&gt;&lt;sys_class_name&gt;sys_variable_value&lt;/sys_class_name&gt;&lt;sys_created_by&gt;admin&lt;/sys_created_by&gt;&lt;sys_created_on&gt;2024-04-17 09:02:13&lt;/sys_created_on&gt;&lt;sys_id&gt;f2ca583ec325021031f0171ed40131fa&lt;/sys_id&gt;&lt;sys_mod_count&gt;4&lt;/sys_mod_count&gt;&lt;sys_updated_by&gt;admin&lt;/sys_updated_by&gt;&lt;sys_updated_on&gt;2024-04-17 09:43:06&lt;/sys_updated_on&gt;&lt;value&gt;state=14^assigned_to={"display":"Fred Luddy","value":"5137153cc611227c000bbd1bd8cd2005","table":"sys_user","sys_id":"5137153cc611227c000bbd1bd8cd2005"}&lt;/value&gt;&lt;variable display_value="Fields"&gt;02d01916c31332002841b63b12d3aeee&lt;/variable&gt;&lt;/sys_variable_value&gt;&lt;sys_element_mapping action="delete_multiple" query="id=a9bad43ec325021031f0171ed40131fc"/&gt;&lt;sys_element_mapping action="INSERT_OR_UPDATE"&gt;&lt;field&gt;record&lt;/field&gt;&lt;id&gt;a9bad43ec325021031f0171ed40131fc&lt;/id&gt;&lt;sys_created_by&gt;admin&lt;/sys_created_by&gt;&lt;sys_created_on&gt;2024-04-17 09:02:13&lt;/sys_created_on&gt;&lt;sys_id&gt;72ca583ec325021031f0171ed40131fa&lt;/sys_id&gt;&lt;sys_mod_count&gt;0&lt;/sys_mod_count&gt;&lt;sys_updated_by&gt;admin&lt;/sys_updated_by&gt;&lt;sys_updated_on&gt;2024-04-17 09:02:13&lt;/sys_updated_on&gt;&lt;table&gt;var__m_sys_hub_action_input_f9d01dd2c31332002841b63b12d3aea1&lt;/table&gt;&lt;value&gt;{{Created_1.current}}&lt;/value&gt;&lt;/sys_element_mapping&gt;&lt;sys_element_mapping action="INSERT_OR_UPDATE"&gt;&lt;field&gt;table_name&lt;/field&gt;&lt;id&gt;a9bad43ec325021031f0171ed40131fc&lt;/id&gt;&lt;sys_created_by&gt;admin&lt;/sys_created_by&gt;&lt;sys_created_on&gt;2024-04-17 09:02:13&lt;/sys_created_on&gt;&lt;sys_id&gt;f6ca583ec325021031f0171ed40131f9&lt;/sys_id&gt;&lt;sys_mod_count&gt;0&lt;/sys_mod_count&gt;&lt;sys_updated_by&gt;admin&lt;/sys_updated_by&gt;&lt;sys_updated_on&gt;2024-04-17 09:02:13&lt;/sys_updated_on&gt;&lt;table&gt;var__m_sys_hub_action_input_f9d01dd2c31332002841b63b12d3aea1&lt;/table&gt;&lt;value/&gt;&lt;/sys_element_mapping&gt;&lt;sys_element_mapping action="INSERT_OR_UPDATE"&gt;&lt;field&gt;values&lt;/field&gt;&lt;id&gt;a9bad43ec325021031f0171ed40131fc&lt;/id&gt;&lt;sys_created_by&gt;admin&lt;/sys_created_by&gt;&lt;sys_created_on&gt;2024-04-17 09:02:13&lt;/sys_created_on&gt;&lt;sys_id&gt;beca583ec325021031f0171ed40131f9&lt;/sys_id&gt;&lt;sys_mod_count&gt;0&lt;/sys_mod_count&gt;&lt;sys_updated_by&gt;admin&lt;/sys_updated_by&gt;&lt;sys_updated_on&gt;2024-04-17 09:02:13&lt;/sys_updated_on&gt;&lt;table&gt;var__m_sys_hub_action_input_f9d01dd2c31332002841b63b12d3aea1&lt;/table&gt;&lt;value/&gt;&lt;/sys_element_mapping&gt;&lt;sys_hub_input_scripts action="delete_multiple" query="instance=a9bad43ec325021031f0171ed40131fc"/&gt;&lt;sys_hub_alias_mapping action="delete_multiple" query="source_id=a9bad43ec325021031f0171ed40131fc"/&gt;&lt;sys_hub_sub_flow_instance action="delete_multiple" query="flow=787a943ac325021031f0171ed4013139"/&gt;&lt;sys_hub_flow_logic action="delete_multiple" query="flow=787a943ac325021031f0171ed4013139^sys_idNOT INd46cd0bec325021031f0171ed40131b0,e6bb987ec325021031f0171ed4013195"/&gt;&lt;sys_hub_flow_logic action="INSERT_OR_UPDATE"&gt;&lt;attributes/&gt;&lt;block display_value=""&gt;c28c9cbec325021031f0171ed40131b4&lt;/block&gt;&lt;comment/&gt;&lt;connected_to&gt;cdfddb15-2229-4aa3-b82e-123e9706b05a&lt;/connected_to&gt;&lt;decision_table/&gt;&lt;decision_table_inputs/&gt;&lt;display_text/&gt;&lt;extended_inputs/&gt;&lt;flow display_value="NeedIt Fulfillment"&gt;787a943ac325021031f0171ed4013139&lt;/flow&gt;&lt;flow_variable/&gt;&lt;flow_variables_assigned/&gt;&lt;generation_source/&gt;&lt;inputs/&gt;&lt;logic_definition display_value="Else"&gt;1f781bf3c32232002841b63b12d3aee6&lt;/logic_definition&gt;&lt;order&gt;5&lt;/order&gt;&lt;outputs_assigned/&gt;&lt;outputs_to_assign/&gt;&lt;parent_ui_id/&gt;&lt;sys_class_name&gt;sys_hub_flow_logic&lt;/sys_class_name&gt;&lt;sys_created_by&gt;admin&lt;/sys_created_by&gt;&lt;sys_created_on&gt;2024-04-17 09:09:09&lt;/sys_created_on&gt;&lt;sys_id&gt;d46cd0bec325021031f0171ed40131b0&lt;/sys_id&gt;&lt;sys_mod_count&gt;3&lt;/sys_mod_count&gt;&lt;sys_scope display_value="NeedIt"&gt;6ead8e780f603200cd674f8ce1050ed1&lt;/sys_scope&gt;&lt;sys_updated_by&gt;admin&lt;/sys_updated_by&gt;&lt;sys_updated_on&gt;2024-04-17 09:09:49&lt;/sys_updated_on&gt;&lt;ui_id&gt;b4a2010b-b985-4530-a999-29fa931b3ad2&lt;/ui_id&gt;&lt;workflow_inputs/&gt;&lt;workflow_reference/&gt;&lt;/sys_hub_flow_logic&gt;&lt;sys_variable_value action="delete_multiple" query="document_key=d46cd0bec325021031f0171ed40131b0"/&gt;&lt;sys_hub_flow_logic_ext_input action="delete_multiple" query="model=d46cd0bec325021031f0171ed40131b0"/&gt;&lt;sys_hub_input_scripts action="delete_multiple" query="instance=d46cd0bec325021031f0171ed40131b0"/&gt;&lt;sys_hub_flow_logic action="INSERT_OR_UPDATE"&gt;&lt;attributes/&gt;&lt;block display_value=""&gt;5d1c18fac325021031f0171ed40131c4&lt;/block&gt;&lt;comment/&gt;&lt;connected_to/&gt;&lt;decision_table/&gt;&lt;decision_table_inputs/&gt;&lt;display_text/&gt;&lt;extended_inputs/&gt;&lt;flow display_value="NeedIt Fulfillment"&gt;787a943ac325021031f0171ed4013139&lt;/flow&gt;&lt;flow_variable/&gt;&lt;flow_variables_assigned/&gt;&lt;generation_source/&gt;&lt;inputs/&gt;&lt;inputs/&gt;&lt;logic_definition display_value="If"&gt;af4e1945c3e232002841b63b12d3ae3e&lt;/logic_definition&gt;&lt;order&gt;3&lt;/order&gt;&lt;outputs_assigned/&gt;&lt;outputs_to_assign/&gt;&lt;parent_ui_id/&gt;&lt;sys_class_name&gt;sys_hub_flow_logic&lt;/sys_class_name&gt;&lt;sys_created_by&gt;admin&lt;/sys_created_by&gt;&lt;sys_created_on&gt;2024-04-17 09:06:18&lt;/sys_created_on&gt;&lt;sys_id&gt;e6bb987ec325021031f0171ed4013195&lt;/sys_id&gt;&lt;sys_mod_count&gt;5&lt;/sys_mod_count&gt;&lt;sys_scope display_value="NeedIt"&gt;6ead8e780f603200cd674f8ce1050ed1&lt;/sys_scope&gt;&lt;sys_updated_by&gt;admin&lt;/sys_updated_by&gt;&lt;sys_updated_on&gt;2024-04-17 09:07:51&lt;/sys_updated_on&gt;&lt;ui_id&gt;cdfddb15-2229-4aa3-b82e-123e9706b05a&lt;/ui_id&gt;&lt;workflow_inputs/&gt;&lt;workflow_reference/&gt;&lt;/sys_hub_flow_logic&gt;&lt;sys_variable_value action="delete_multiple" query="document_key=e6bb987ec325021031f0171ed4013195"/&gt;&lt;sys_variable_value action="INSERT_OR_UPDATE"&gt;&lt;document&gt;sys_hub_flow_logic&lt;/document&gt;&lt;document_key&gt;e6bb987ec325021031f0171ed4013195&lt;/document_key&gt;&lt;order&gt;10&lt;/order&gt;&lt;sys_class_name&gt;sys_variable_value&lt;/sys_class_name&gt;&lt;sys_created_by&gt;admin&lt;/sys_created_by&gt;&lt;sys_created_on&gt;2024-04-17 09:07:30&lt;/sys_created_on&gt;&lt;sys_id&gt;040cd0bec325021031f0171ed401317f&lt;/sys_id&gt;&lt;sys_mod_count&gt;0&lt;/sys_mod_count&gt;&lt;sys_updated_by&gt;admin&lt;/sys_updated_by&gt;&lt;sys_updated_on&gt;2024-04-17 09:07:30&lt;/sys_updated_on&gt;&lt;value&gt;Request Approved&lt;/value&gt;&lt;variable display_value="Condition Label"&gt;f0af19c1c32632002841b63b12d3aea3&lt;/variable&gt;&lt;/sys_variable_value&gt;&lt;sys_element_mapping action="delete_multiple" query="id=e6bb987ec325021031f0171ed4013195"/&gt;&lt;sys_element_mapping action="INSERT_OR_UPDATE"&gt;&lt;field&gt;condition&lt;/field&gt;&lt;id&gt;e6bb987ec325021031f0171ed4013195&lt;/id&gt;&lt;sys_created_by&gt;admin&lt;/sys_created_by&gt;&lt;sys_created_on&gt;2024-04-17 09:07:30&lt;/sys_created_on&gt;&lt;sys_id&gt;800cd0bec325021031f0171ed401317f&lt;/sys_id&gt;&lt;sys_mod_count&gt;0&lt;/sys_mod_count&gt;&lt;sys_updated_by&gt;admin&lt;/sys_updated_by&gt;&lt;sys_updated_on&gt;2024-04-17 09:07:30&lt;/sys_updated_on&gt;&lt;table&gt;var__m_sys_hub_flow_logic_input_af4e1945c3e232002841b63b12d3ae3e&lt;/table&gt;&lt;value&gt;{{74cdd38d-6c6f-49fa-86d4-7a41eceab24a.approval_state}}=approved&lt;/value&gt;&lt;/sys_element_mapping&gt;&lt;sys_element_mapping action="INSERT_OR_UPDATE"&gt;&lt;field&gt;condition_name&lt;/field&gt;&lt;id&gt;e6bb987ec325021031f0171ed4013195&lt;/id&gt;&lt;sys_created_by&gt;admin&lt;/sys_created_by&gt;&lt;sys_created_on&gt;2024-04-17 09:07:30&lt;/sys_created_on&gt;&lt;sys_id&gt;cc0cd0bec325021031f0171ed401317e&lt;/sys_id&gt;&lt;sys_mod_count&gt;0&lt;/sys_mod_count&gt;&lt;sys_updated_by&gt;admin&lt;/sys_updated_by&gt;&lt;sys_updated_on&gt;2024-04-17 09:07:30&lt;/sys_updated_on&gt;&lt;table&gt;var__m_sys_hub_flow_logic_input_af4e1945c3e232002841b63b12d3ae3e&lt;/table&gt;&lt;value/&gt;&lt;/sys_element_mapping&gt;&lt;sys_hub_flow_logic_ext_input action="delete_multiple" query="model=e6bb987ec325021031f0171ed4013195"/&gt;&lt;sys_hub_input_scripts action="delete_multiple" query="instance=e6bb987ec325021031f0171ed4013195"/&gt;&lt;sys_hub_pill_compound action="delete_multiple" query="attached_to=787a943ac325021031f0171ed4013139"/&gt;&lt;sys_hub_flow_variable action="delete_multiple" query="model=787a943ac325021031f0171ed4013139"/&gt;&lt;sys_documentation action="delete_multiple" query="name=var__m_sys_hub_flow_input_787a943ac325021031f0171ed4013139^sys_idNOT IN2decd4fec325021031f0171ed40131a4,59ecd4fec325021031f0171ed4013190"/&gt;&lt;sys_documentation action="INSERT_OR_UPDATE"&gt;&lt;element&gt;table_name&lt;/element&gt;&lt;help/&gt;&lt;hint/&gt;&lt;label&gt;Table Name&lt;/label&gt;&lt;language&gt;en&lt;/language&gt;&lt;name&gt;var__m_sys_hub_flow_input_787a943ac325021031f0171ed4013139&lt;/name&gt;&lt;plural/&gt;&lt;sys_class_name&gt;sys_documentation&lt;/sys_class_name&gt;&lt;sys_created_by&gt;admin&lt;/sys_created_by&gt;&lt;sys_created_on&gt;2024-04-17 09:11:25&lt;/sys_created_on&gt;&lt;sys_id&gt;2decd4fec325021031f0171ed40131a4&lt;/sys_id&gt;&lt;sys_mod_count&gt;0&lt;/sys_mod_count&gt;&lt;sys_name/&gt;&lt;sys_package display_value="NeedIt" source="x_58872_needit"&gt;6ead8e780f603200cd674f8ce1050ed1&lt;/sys_package&gt;&lt;sys_policy/&gt;&lt;sys_scope display_value="NeedIt"&gt;6ead8e780f603200cd674f8ce1050ed1&lt;/sys_scope&gt;&lt;sys_update_name/&gt;&lt;sys_updated_by&gt;admin&lt;/sys_updated_by&gt;&lt;sys_updated_on&gt;2024-04-17 09:11:25&lt;/sys_updated_on&gt;&lt;url/&gt;&lt;url_target/&gt;&lt;/sys_documentation&gt;&lt;sys_documentation action="INSERT_OR_UPDATE"&gt;&lt;element&gt;current&lt;/element&gt;&lt;help/&gt;&lt;hint/&gt;&lt;label&gt;Record&lt;/label&gt;&lt;language&gt;en&lt;/language&gt;&lt;name&gt;var__m_sys_hub_flow_input_787a943ac325021031f0171ed4013139&lt;/name&gt;&lt;plural/&gt;&lt;sys_class_name&gt;sys_documentation&lt;/sys_class_name&gt;&lt;sys_created_by&gt;admin&lt;/sys_created_by&gt;&lt;sys_created_on&gt;2024-04-17 09:11:25&lt;/sys_created_on&gt;&lt;sys_id&gt;59ecd4fec325021031f0171ed4013190&lt;/sys_id&gt;&lt;sys_mod_count&gt;0&lt;/sys_mod_count&gt;&lt;sys_name/&gt;&lt;sys_package display_value="NeedIt" source="x_58872_needit"&gt;6ead8e780f603200cd674f8ce1050ed1&lt;/sys_package&gt;&lt;sys_policy/&gt;&lt;sys_scope display_value="NeedIt"&gt;6ead8e780f603200cd674f8ce1050ed1&lt;/sys_scope&gt;&lt;sys_update_name/&gt;&lt;sys_updated_by&gt;admin&lt;/sys_updated_by&gt;&lt;sys_updated_on&gt;2024-04-17 09:11:25&lt;/sys_updated_on&gt;&lt;url/&gt;&lt;url_target/&gt;&lt;/sys_documentation&gt;&lt;sys_choice action="delete_multiple" query="name=var__m_sys_hub_flow_input_787a943ac325021031f0171ed4013139"/&gt;&lt;sys_documentation action="delete_multiple" query="name=var__m_sys_hub_flow_output_787a943ac325021031f0171ed4013139"/&gt;&lt;sys_choice action="delete_multiple" query="name=var__m_sys_hub_flow_output_787a943ac325021031f0171ed4013139"/&gt;&lt;sys_flow_trigger_plan action="delete_multiple" query="plan_id=787a943ac325021031f0171ed4013139"/&gt;&lt;sys_flow_subflow_plan action="delete_multiple" query="plan_id=787a943ac325021031f0171ed4013139"/&gt;&lt;/record_update&gt;</payload>
        <payload_hash>1436474966</payload_hash>
        <record_name>NeedIt Fulfillment</record_name>
        <reverted_from/>
        <source>5c7781b5c361021031f0171ed40131c0</source>
        <source_table>sys_update_set</source_table>
        <state>previous</state>
        <sys_created_by>admin</sys_created_by>
        <sys_created_on>2024-04-17 09:43:17</sys_created_on>
        <sys_id>9034287ac365021031f0171ed4013189</sys_id>
        <sys_mod_count>0</sys_mod_count>
        <sys_recorded_at>18eeb706b490000001</sys_recorded_at>
        <sys_updated_by>admin</sys_updated_by>
        <sys_updated_on>2024-04-17 09:43:17</sys_updated_on>
        <type>Flow</type>
        <update_guid>0834287a8c6502107b39c8a5f72a0e88</update_guid>
        <update_guid_history>0834287a8c6502107b39c8a5f72a0e88:1436474966,00322cb60f6502109a8f065ef07a7618:743909328,0d51a876f8650210ccbd96246cb908e2:266705781,08be10b2a6650210b42129884c185a55:659675161,16ac50fed7250210f18ad988cdc179a7:-294637464,638cdcbefd250210d6efb5d0d12ae93e:207321561,f86cd8bed52502103c83b27b45362798:-825435165,2f3c18bedd250210e3dfdfea2d95e77f:519150277,e31c94be6a250210581f250589508b0b:233155,be0c14bec625021067f22a1f3e64845f:1047705309,41fb90be3a2502101dbddf44b0167002:2135800749,4dcb9c7efa25021027395e55894efd5f:-888226372,6ebb5c7ef4250210fc126dd8e065ac22:1402956183,e99b987e432502100685635d0af7a38d:293124597,688b187e43250210227f5319d05da4ae:-897286987,3e5b547e392502104e8e989d975dc2d5:-815663796,2a3bd07eeb2502103751930daf671605:-15248060,3c3b907e8f2502103476f5944b527070:1015586199,51da983e912502100098990a7fe789ad:40341759,4fba183e64250210f9eea7d880db45a0:779353606,71bad43e0a25021056838eabc378f5ec:511480615,fc7a503eb125021004bb71a544e4e190:1684519641</update_guid_history>
    </sys_update_version>
    <sys_metadata_delete action="INSERT_OR_UPDATE">
        <sys_audit_delete/>
        <sys_class_name>sys_metadata_delete</sys_class_name>
        <sys_created_by>admin</sys_created_by>
        <sys_created_on>2024-04-17 09:45:28</sys_created_on>
        <sys_db_object display_value="" name="sys_hub_flow">sys_hub_flow</sys_db_object>
        <sys_id>42ee643396274c4da66b0e3ef87ae329</sys_id>
        <sys_metadata>787a943ac325021031f0171ed4013139</sys_metadata>
        <sys_mod_count>0</sys_mod_count>
        <sys_name>NeedIt Fulfillment</sys_name>
        <sys_package display_value="NeedIt" source="x_58872_needit">6ead8e780f603200cd674f8ce1050ed1</sys_package>
        <sys_parent/>
        <sys_policy/>
        <sys_scope display_value="NeedIt">6ead8e780f603200cd674f8ce1050ed1</sys_scope>
        <sys_scope_delete display_value="">94872a8897db403e8ee69a431de2fca4</sys_scope_delete>
        <sys_update_name>sys_hub_flow_787a943ac325021031f0171ed4013139</sys_update_name>
        <sys_update_version display_value="sys_hub_flow_787a943ac325021031f0171ed4013139">9034287ac365021031f0171ed4013189</sys_update_version>
        <sys_updated_by>admin</sys_updated_by>
        <sys_updated_on>2024-04-17 09:45:28</sys_updated_on>
    </sys_metadata_delete>
</record_update>
